{
  "07930f97-c467-426a-bfc5-4ab1006bd9bf": {
    "id": "07930f97-c467-426a-bfc5-4ab1006bd9bf",
    "parent_id": null,
    "level": 0,
    "title": "77990",
    "block_number": "",
    "knowledge_summary": "知识点: 燃煤电厂、环保数据、电网接入技术规范、烟气脱硫、脱硫监测数据、系统构成、功能、数据采集、处理、性能指标、原则、技术要求、并网、火电厂、规范性引用文件、不间断电源设备、操作人员触及区、UPS、一般规定、安全要求、电力监控系统、网络安全防护导则、远动设备及系统、传输规约、火力发电厂厂级监控信息系统技术条件、电力调度数据网技术规范、固定污染源烟气排放、连续监测系统技术要求、检测方法、术语和定义、主站、监测信息、集中节点、子站、综合分析、硬件设备、应用软件、总则、运行条件\n\n摘要: 本章节深入探讨了燃煤电厂环保数据接入电网的技术规范，涵盖了烟气脱硫监测数据的系统构成、功能、数据采集处理及性能指标等原则和技术要求。内容还包括了规范性文件的引用、不间断电源设备的安全规定、电力监控系统网络安全防护导则、远动设备及系统传输规约、火力发电厂厂级监控信息系统技术条件、电力调度数据网技术规范、固定污染源烟气排放连续监测系统技术要求及检测方法。此外，还定义了相关术语和定义，如主站、监测信息、集中节点、子站等，并对烟气脱硫技术的运行条件、系统构成、功能、数据采集、处理以及性能指标进行了详细阐述。",
    "page_content": "",
    "children": [
      "98e6af9c-3ef4-4c1a-8a4a-1ac15da75508",
      "a4beb721-e78a-4210-9d3d-8a098bfba092",
      "94395aaa-1188-43e9-8db2-8d4bf2e1432e",
      "90034d38-cc03-4735-aaf3-42019c346c6f",
      "cb96e128-e9b8-47ac-8019-80a9e62eb991",
      "b0c95d46-936a-4ade-a5d5-475d02b78eb2",
      "fa67dd51-4741-4981-80b9-1354dff2a7ef",
      "856a56e3-b2aa-40dc-a58a-591c750b0ec4"
    ],
    "embedding": [],
    "metadata": {
      "child_knowledge": [
        {
          "title": "1",
          "summary": "知识点：燃煤电厂、环保数据、电网接入技术规范、烟气脱硫、脱硫监测数据、系统构成、功能、数据采集、处理、性能指标、原则、技术要求、并网、火电厂\n\n摘要：本段内容讲述了关于燃煤电厂环保数据接入电网的技术规范，特别是烟气脱硫监测数据的系统构成、功能、数据采集处理及性能指标等原则和技术要求，并指出此规范适用于并网燃煤电厂，其他火电厂也可参照执行。"
        },
        {
          "title": "2",
          "summary": "知识点：燃煤电厂环保数据、电网接入技术规范、烟气脱硫、规范性引用文件、GB7260.1、不间断电源设备、操作人员触及区、UPS、一般规定、安全要求、GB/T36572-2018、电力监控系统、网络安全防护导则、DL/T634.5101、远动设备及系统、传输规约、DL/T634.5104、传输规约、采用标准传输协议集、IEC60870-5-101、网络访问、DL/T924-2016、火力发电厂厂级监控信息系统技术条件、DL/T1306-2013、电力调度数据网技术规范、HJ76-2017、固定污染源烟气排放、连续监测系统技术要求、检测方法。\n\n摘要：本段内容介绍了燃煤电厂环保数据电网接入技术规范中引用的规范性文件，包括不间断电源设备的安全规定、电力监控系统网络安全防护导则、远动设备及系统传输规约、火力发电厂厂级监控信息系统技术条件、电力调度数据网技术规范以及固定污染源烟气排放连续监测系统技术要求及检测方法等。"
        },
        {
          "title": "3",
          "summary": "知识点：燃煤电厂、环保数据、电网接入技术规范、烟气脱硫、术语和定义、主站、监测信息、集中节点、子站、脱硫监测数据、综合分析、硬件设备、应用软件\n\n摘要：本段内容讲述了燃煤电厂环保数据电网接入技术规范中关于烟气脱硫的相关术语和定义，包括主站作为监测信息的集中节点，收集各子站的脱硫监测数据，并进行综合分析的硬件设备及应用软件。"
        },
        {
          "title": "4",
          "summary": "知识点：燃煤电厂、环保数据、电网接入技术规范、烟气脱硫、总则\n\n摘要：本段内容讲述了关于燃煤电厂的环保数据、电网接入技术规范以及烟气脱硫的总则性规定。"
        },
        {
          "title": "5",
          "summary": "知识点：燃煤电厂、环保数据、电网接入技术规范、烟气脱硫、运行条件\n摘要：该段落讲述了关于燃煤电厂在环保数据和电网接入技术规范方面，特别是烟气脱硫技术的运行条件的相关内容。"
        },
        {
          "title": "6",
          "summary": "知识点：燃煤电厂、环保数据、电网接入技术规范、烟气脱硫、系统构成、功能\n\n摘要：本段讲述了关于燃煤电厂环保数据电网接入技术规范中的烟气脱硫系统，包括系统的构成和功能。"
        },
        {
          "title": "7",
          "summary": "知识点：燃煤电厂、环保数据、电网接入技术规范、烟气脱硫、数据采集、数据处理\n摘要：该段落讲述了关于燃煤电厂的环保数据，包括电网接入技术规范中的烟气脱硫环节，以及数据采集和处理的有关内容。"
        },
        {
          "title": "8",
          "summary": "知识点：燃煤电厂、环保数据、电网接入技术规范、烟气脱硫、性能指标\n\n摘要：本段内容讲述了关于燃煤电厂环保数据、电网接入技术规范以及烟气脱硫的相关性能指标。"
        }
      ]
    }
  },
  "98e6af9c-3ef4-4c1a-8a4a-1ac15da75508": {
    "id": "98e6af9c-3ef4-4c1a-8a4a-1ac15da75508",
    "parent_id": "07930f97-c467-426a-bfc5-4ab1006bd9bf",
    "level": 1,
    "title": "1",
    "block_number": "1",
    "knowledge_summary": "知识点：燃煤电厂、环保数据、电网接入技术规范、烟气脱硫、脱硫监测数据、系统构成、功能、数据采集、处理、性能指标、原则、技术要求、并网、火电厂\n\n摘要：本段内容讲述了关于燃煤电厂环保数据接入电网的技术规范，特别是烟气脱硫监测数据的系统构成、功能、数据采集处理及性能指标等原则和技术要求，并指出此规范适用于并网燃煤电厂，其他火电厂也可参照执行。",
    "page_content": "燃煤电厂环保数据电网接入技术规范 烟气脱硫 > 范围本文件规定了脱硫监测数据接入系统的构成及功能、数据采集和处理、性能指标等原则和技术要求。本文件适用于并网燃煤电厂，其他火电厂可参照执行。",
    "children": [],
    "embedding": [],
    "metadata": {
      "original_level": 1
    }
  },
  "a4beb721-e78a-4210-9d3d-8a098bfba092": {
    "id": "a4beb721-e78a-4210-9d3d-8a098bfba092",
    "parent_id": "07930f97-c467-426a-bfc5-4ab1006bd9bf",
    "level": 1,
    "title": "2",
    "block_number": "2",
    "knowledge_summary": "知识点：燃煤电厂环保数据、电网接入技术规范、烟气脱硫、规范性引用文件、GB7260.1、不间断电源设备、操作人员触及区、UPS、一般规定、安全要求、GB/T36572-2018、电力监控系统、网络安全防护导则、DL/T634.5101、远动设备及系统、传输规约、DL/T634.5104、传输规约、采用标准传输协议集、IEC60870-5-101、网络访问、DL/T924-2016、火力发电厂厂级监控信息系统技术条件、DL/T1306-2013、电力调度数据网技术规范、HJ76-2017、固定污染源烟气排放、连续监测系统技术要求、检测方法。\n\n摘要：本段内容介绍了燃煤电厂环保数据电网接入技术规范中引用的规范性文件，包括不间断电源设备的安全规定、电力监控系统网络安全防护导则、远动设备及系统传输规约、火力发电厂厂级监控信息系统技术条件、电力调度数据网技术规范以及固定污染源烟气排放连续监测系统技术要求及检测方法等。",
    "page_content": "燃煤电厂环保数据电网接入技术规范 烟气脱硫 > 规范性引用文件下列文件中的内容通过文中的规范性引用而构成本文件必不可少的条款。其中，注日期的引用文件，仅该日期对应的版本适用于本文件；不注日期的引用文件，其最新版本（包括所有的修改单）适用于本文件。GB7260.1 不间断电源设备 第 1-1 部分：操作人员触及区使用的 UPS 的一般规定和安全要求GB/T36572-2018 电力监控系统网络安全防护导则DL/T634.5101 远动设备及系统 第 5-101 部分：传输规约DL/T634.5104 远动设备及系统 第 5-104 部分：传输规约采用标准传输协议集的 IEC60870-5-101网络访问DL/T924-2016 火力发电厂厂级监控信息系统技术条件DL/T1306-2013 电力调度数据网技术规范HJ76-2017 固定污染源烟气（SO2、NOX、颗粒物）排放连续监测系统技术要求及检测方法",
    "children": [],
    "embedding": [],
    "metadata": {
      "original_level": 1
    }
  },
  "94395aaa-1188-43e9-8db2-8d4bf2e1432e": {
    "id": "94395aaa-1188-43e9-8db2-8d4bf2e1432e",
    "parent_id": "07930f97-c467-426a-bfc5-4ab1006bd9bf",
    "level": 1,
    "title": "3",
    "block_number": "3",
    "knowledge_summary": "知识点：燃煤电厂、环保数据、电网接入技术规范、烟气脱硫、术语和定义、主站、监测信息、集中节点、子站、脱硫监测数据、综合分析、硬件设备、应用软件\n\n摘要：本段内容讲述了燃煤电厂环保数据电网接入技术规范中关于烟气脱硫的相关术语和定义，包括主站作为监测信息的集中节点，收集各子站的脱硫监测数据，并进行综合分析的硬件设备及应用软件。\n\n【子节点综合】\n知识点: 燃煤电厂、环保数据、电网接入技术规范、烟气脱硫、术语和定义、主站、监测信息、集中节点、子站、脱硫监测数据、综合分析、硬件设备、应用软件、生产控制大区、数据采集与控制、纵向联接、专用网络、专用通道、电力监控系统、安全区域、管理信息大区、办公自动化系统、信息网络、GB/T36572-2018\n\n摘要: 本章节详细阐述了燃煤电厂环保数据电网接入技术规范中烟气脱硫的相关术语和定义，涵盖了主站作为监测信息的集中节点，各子站脱硫监测数据的采集、上传、综合分析及硬件设备和应用软件的使用，同时描述了生产控制大区、数据采集与控制、纵向联接、专用网络和专用通道等概念，以及管理信息大区、办公自动化系统和信息网络的相关内容，并引用了相关标准GB/T36572-2018。",
    "page_content": "燃煤电厂环保数据电网接入技术规范 烟气脱硫 > 术语和定义下列术语和定义适用于本文件。主站master station监测信息的集中节点，收集各子站脱硫监测数据，并进行综合分析的硬件设备及应用软",
    "children": [
      "9a38f2ad-84b6-483a-9650-af6f7a7deafc",
      "44f1654b-4c16-442e-aaa3-6d0329e087e0",
      "c1d96944-a659-4354-9187-a6527afebafa",
      "27f2b9cc-bed5-4e97-83e1-858c5603e299"
    ],
    "embedding": [],
    "metadata": {
      "original_level": 1,
      "child_knowledge": [
        {
          "title": "3.1",
          "summary": "知识点：燃煤电厂、环保数据、电网接入技术规范、烟气脱硫、术语和定义、主站、监测信息、集中节点、子站、脱硫监测数据、综合分析、硬件设备、应用软件\n\n摘要：本段内容讲述了燃煤电厂环保数据电网接入技术规范中关于烟气脱硫的术语和定义，包括主站作为监测信息的集中节点，收集各子站的脱硫监测数据，并利用硬件设备和应用软件进行综合分析。"
        },
        {
          "title": "3.2",
          "summary": "知识点：燃煤电厂、环保数据、电网接入技术规范、烟气脱硫、术语和定义、主站、监测信息、集中节点、子站、监测数据、采集、上传、电厂侧、硬件设备、应用软件。\n\n摘要：本段内容介绍了燃煤电厂环保数据电网接入技术规范中关于烟气脱硫的术语和定义，包括主站和子站的定义及其在监测信息采集和上传中的作用，以及相关硬件设备和应用软件。"
        },
        {
          "title": "3.3",
          "summary": "知识点：燃煤电厂、环保数据、电网接入技术规范、烟气脱硫、术语和定义、主站、监测信息、集中节点、子站、脱硫监测数据、综合分析、硬件设备、应用、生产控制大区、数据采集与控制、纵向联接、专用网络、专用通道、电力监控系统、安全区域\n\n摘要：本段内容讲述了燃煤电厂环保数据电网接入技术规范中的术语和定义，包括主站作为监测信息的集中节点，收集各子站脱硫监测数据并进行综合分析的硬件设备及应用，以及生产控制大区由具有数据采集与控制功能、纵向联接使用专用网络或专用通道的电力监控系统构成的安全区域。"
        },
        {
          "title": "3.4",
          "summary": "知识点：燃煤电厂、环保数据、电网接入技术规范、烟气脱硫、术语和定义、主站、监测信息、集中节点、子站、脱硫监测数据、综合分析、硬件设备、应用、DL/TXXXXX－20XX、管理信息大区、生产控制大区、企业管理、办公自动化系统、信息网络、安全区域、GB/T36572-2018\n\n摘要：本段内容讲述了燃煤电厂环保数据电网接入技术规范中关于烟气脱硫的术语和定义，包括主站、监测信息、集中节点、子站、脱硫监测数据、综合分析、硬件设备、应用等概念，以及DL/TXXXXX－20XX管理信息大区和管理信息大区的定义，并引用了GB/T36572-2018标准。"
        }
      ]
    }
  },
  "9a38f2ad-84b6-483a-9650-af6f7a7deafc": {
    "id": "9a38f2ad-84b6-483a-9650-af6f7a7deafc",
    "parent_id": "94395aaa-1188-43e9-8db2-8d4bf2e1432e",
    "level": 2,
    "title": "3.1",
    "block_number": "3.1",
    "knowledge_summary": "知识点：燃煤电厂、环保数据、电网接入技术规范、烟气脱硫、术语和定义、主站、监测信息、集中节点、子站、脱硫监测数据、综合分析、硬件设备、应用软件\n\n摘要：本段内容讲述了燃煤电厂环保数据电网接入技术规范中关于烟气脱硫的术语和定义，包括主站作为监测信息的集中节点，收集各子站的脱硫监测数据，并利用硬件设备和应用软件进行综合分析。",
    "page_content": "燃煤电厂环保数据电网接入技术规范 烟气脱硫 > 术语和定义下列术语和定义适用于本文件主站master station监测信息的集中节点，收集各子站脱硫监测数据，并进行综合分析的硬件设备及应用软 > 件。",
    "children": [],
    "embedding": [],
    "metadata": {
      "original_level": 2
    }
  },
  "44f1654b-4c16-442e-aaa3-6d0329e087e0": {
    "id": "44f1654b-4c16-442e-aaa3-6d0329e087e0",
    "parent_id": "94395aaa-1188-43e9-8db2-8d4bf2e1432e",
    "level": 2,
    "title": "3.2",
    "block_number": "3.2",
    "knowledge_summary": "知识点：燃煤电厂、环保数据、电网接入技术规范、烟气脱硫、术语和定义、主站、监测信息、集中节点、子站、监测数据、采集、上传、电厂侧、硬件设备、应用软件。\n\n摘要：本段内容介绍了燃煤电厂环保数据电网接入技术规范中关于烟气脱硫的术语和定义，包括主站和子站的定义及其在监测信息采集和上传中的作用，以及相关硬件设备和应用软件。",
    "page_content": "燃煤电厂环保数据电网接入技术规范 烟气脱硫 > 术语和定义下列术语和定义适用于本文件主站master station监测信息的集中节点，收集各子站脱硫监测数据，并进行综合分析的硬件设备及应用软 > 子站sub-station监测信息的采集及上传节点，部署在电厂侧与主站共同完成脱硫监测数据接入的硬件设备及应用软件。",
    "children": [],
    "embedding": [],
    "metadata": {
      "original_level": 2
    }
  },
  "c1d96944-a659-4354-9187-a6527afebafa": {
    "id": "c1d96944-a659-4354-9187-a6527afebafa",
    "parent_id": "94395aaa-1188-43e9-8db2-8d4bf2e1432e",
    "level": 2,
    "title": "3.3",
    "block_number": "3.3",
    "knowledge_summary": "知识点：燃煤电厂、环保数据、电网接入技术规范、烟气脱硫、术语和定义、主站、监测信息、集中节点、子站、脱硫监测数据、综合分析、硬件设备、应用、生产控制大区、数据采集与控制、纵向联接、专用网络、专用通道、电力监控系统、安全区域\n\n摘要：本段内容讲述了燃煤电厂环保数据电网接入技术规范中的术语和定义，包括主站作为监测信息的集中节点，收集各子站脱硫监测数据并进行综合分析的硬件设备及应用，以及生产控制大区由具有数据采集与控制功能、纵向联接使用专用网络或专用通道的电力监控系统构成的安全区域。",
    "page_content": "燃煤电厂环保数据电网接入技术规范 烟气脱硫 > 术语和定义下列术语和定义适用于本文件主站master station监测信息的集中节点，收集各子站脱硫监测数据，并进行综合分析的硬件设备及应用软 > 生产控制大区protection control zone由具有数据采集与控制功能、纵向联接使用专用网络或专用通道的电力监控系统构成的安全区域。［来源：GB/T36572-2018, 3.3］",
    "children": [],
    "embedding": [],
    "metadata": {
      "original_level": 2
    }
  },
  "27f2b9cc-bed5-4e97-83e1-858c5603e299": {
    "id": "27f2b9cc-bed5-4e97-83e1-858c5603e299",
    "parent_id": "94395aaa-1188-43e9-8db2-8d4bf2e1432e",
    "level": 2,
    "title": "3.4",
    "block_number": "3.4",
    "knowledge_summary": "知识点：燃煤电厂、环保数据、电网接入技术规范、烟气脱硫、术语和定义、主站、监测信息、集中节点、子站、脱硫监测数据、综合分析、硬件设备、应用、DL/TXXXXX－20XX、管理信息大区、生产控制大区、企业管理、办公自动化系统、信息网络、安全区域、GB/T36572-2018\n\n摘要：本段内容讲述了燃煤电厂环保数据电网接入技术规范中关于烟气脱硫的术语和定义，包括主站、监测信息、集中节点、子站、脱硫监测数据、综合分析、硬件设备、应用等概念，以及DL/TXXXXX－20XX管理信息大区和管理信息大区的定义，并引用了GB/T36572-2018标准。",
    "page_content": "燃煤电厂环保数据电网接入技术规范 烟气脱硫 > 术语和定义下列术语和定义适用于本文件主站master station监测信息的集中节点，收集各子站脱硫监测数据，并进行综合分析的硬件设备及应用软 > DL/TXXXXX－20XX管理信息大区management information zone生产控制大区之外，主要由企业管理、办公自动化系统及信息网络构成的安全区域。［来源：GB/T36572-2018, 3.6］",
    "children": [],
    "embedding": [],
    "metadata": {
      "original_level": 2
    }
  },
  "90034d38-cc03-4735-aaf3-42019c346c6f": {
    "id": "90034d38-cc03-4735-aaf3-42019c346c6f",
    "parent_id": "07930f97-c467-426a-bfc5-4ab1006bd9bf",
    "level": 1,
    "title": "4",
    "block_number": "4",
    "knowledge_summary": "知识点：燃煤电厂、环保数据、电网接入技术规范、烟气脱硫、总则\n\n摘要：本段内容讲述了关于燃煤电厂的环保数据、电网接入技术规范以及烟气脱硫的总则性规定。\n\n【子节点综合】\n知识点: 燃煤电厂、环保数据、电网接入技术规范、烟气脱硫、脱硫监测数据、接入系统、开放式体系结构、可扩展性、易维护性、脱硫及监测技术、发展完善、系统配置、通用、成熟、稳定可靠、实时多任务操作系统、标准化接口技术、数据共享、电力监控系统、安全防护要求\n\n摘要: 当前章节详细阐述了燃煤电厂环保数据电网接入技术规范中关于烟气脱硫的相关要求，包括脱硫监测数据的接入系统应采用开放式体系结构以确保可扩展性和易维护性，系统配置需采用通用、成熟、稳定可靠的实时多任务操作系统，同时强调采用标准化接口技术实现数据共享，并符合电力监控系统安全防护要求，以确保脱硫及监测技术的持续发展完善。",
    "page_content": "燃煤电厂环保数据电网接入技术规范 烟气脱硫 > 总则",
    "children": [
      "594c01c0-a105-4a82-8e86-c52bc2e9d791",
      "651d2d2c-9fa6-4e64-9090-3f08f2bfccbf",
      "ada0bda8-ec10-4b5a-baf6-4c10a9afb030",
      "bc0fa8b4-b88a-42c4-b967-8c62b1e80838"
    ],
    "embedding": [],
    "metadata": {
      "original_level": 1,
      "child_knowledge": [
        {
          "title": "4.1",
          "summary": "知识点：燃煤电厂、环保数据、电网接入技术规范、烟气脱硫、脱硫监测数据、接入系统、开放式体系结构、可扩展性、易维护性、脱硫及监测技术、发展完善\n\n摘要：本段内容讲述了燃煤电厂环保数据电网接入技术规范中关于烟气脱硫监测数据接入系统的要求，强调了系统应采用开放式体系结构，以保证其可扩展性和易维护性，以适应脱硫及监测技术的发展和完善。"
        },
        {
          "title": "4.2",
          "summary": "知识点：燃煤电厂、环保数据、电网接入技术规范、烟气脱硫、总则、系统配置、通用、成熟、稳定可靠、实时多任务操作系统\n\n摘要：本段落讲述了燃煤电厂环保数据电网接入技术规范中关于烟气脱硫系统的配置要求，强调系统应采用通用、成熟、稳定可靠的实时多任务操作系统。"
        },
        {
          "title": "4.3",
          "summary": "知识点：燃煤电厂、环保数据、电网接入技术规范、烟气脱硫、标准化接口技术、数据共享\n\n摘要：本段内容讲述了燃煤电厂在烟气脱硫过程中，应采用标准化的接口技术，以实现与其他系统之间的数据共享，满足电网接入技术规范的要求。"
        },
        {
          "title": "4.4",
          "summary": "知识点：燃煤电厂、环保数据、电网接入技术规范、烟气脱硫、总则、系统、电力监控系统、安全防护要求\n\n摘要：本段内容讲述了燃煤电厂环保数据电网接入技术规范中关于烟气脱硫系统的总则要求，强调了系统必须符合电力监控系统安全防护的要求。"
        }
      ]
    }
  },
  "594c01c0-a105-4a82-8e86-c52bc2e9d791": {
    "id": "594c01c0-a105-4a82-8e86-c52bc2e9d791",
    "parent_id": "90034d38-cc03-4735-aaf3-42019c346c6f",
    "level": 2,
    "title": "4.1",
    "block_number": "4.1",
    "knowledge_summary": "知识点：燃煤电厂、环保数据、电网接入技术规范、烟气脱硫、脱硫监测数据、接入系统、开放式体系结构、可扩展性、易维护性、脱硫及监测技术、发展完善\n\n摘要：本段内容讲述了燃煤电厂环保数据电网接入技术规范中关于烟气脱硫监测数据接入系统的要求，强调了系统应采用开放式体系结构，以保证其可扩展性和易维护性，以适应脱硫及监测技术的发展和完善。",
    "page_content": "燃煤电厂环保数据电网接入技术规范 烟气脱硫 > 总则 > 脱硫监测数据接入系统（以下简称：系统）应采用开放式体系结构，保证系统的可扩展性和易维护性，能适应脱硫及监测技术发展完善的需要。",
    "children": [],
    "embedding": [],
    "metadata": {
      "original_level": 2
    }
  },
  "651d2d2c-9fa6-4e64-9090-3f08f2bfccbf": {
    "id": "651d2d2c-9fa6-4e64-9090-3f08f2bfccbf",
    "parent_id": "90034d38-cc03-4735-aaf3-42019c346c6f",
    "level": 2,
    "title": "4.2",
    "block_number": "4.2",
    "knowledge_summary": "知识点：燃煤电厂、环保数据、电网接入技术规范、烟气脱硫、总则、系统配置、通用、成熟、稳定可靠、实时多任务操作系统\n\n摘要：本段落讲述了燃煤电厂环保数据电网接入技术规范中关于烟气脱硫系统的配置要求，强调系统应采用通用、成熟、稳定可靠的实时多任务操作系统。",
    "page_content": "燃煤电厂环保数据电网接入技术规范 烟气脱硫 > 总则 > 系统应配置通用的、成熟的、稳定可靠的、实时多任务操作系统。",
    "children": [],
    "embedding": [],
    "metadata": {
      "original_level": 2
    }
  },
  "ada0bda8-ec10-4b5a-baf6-4c10a9afb030": {
    "id": "ada0bda8-ec10-4b5a-baf6-4c10a9afb030",
    "parent_id": "90034d38-cc03-4735-aaf3-42019c346c6f",
    "level": 2,
    "title": "4.3",
    "block_number": "4.3",
    "knowledge_summary": "知识点：燃煤电厂、环保数据、电网接入技术规范、烟气脱硫、标准化接口技术、数据共享\n\n摘要：本段内容讲述了燃煤电厂在烟气脱硫过程中，应采用标准化的接口技术，以实现与其他系统之间的数据共享，满足电网接入技术规范的要求。",
    "page_content": "燃煤电厂环保数据电网接入技术规范 烟气脱硫 > 总则 > 系统应采用标准化的接口技术，满足与其他系统的数据共享要求。",
    "children": [],
    "embedding": [],
    "metadata": {
      "original_level": 2
    }
  },
  "bc0fa8b4-b88a-42c4-b967-8c62b1e80838": {
    "id": "bc0fa8b4-b88a-42c4-b967-8c62b1e80838",
    "parent_id": "90034d38-cc03-4735-aaf3-42019c346c6f",
    "level": 2,
    "title": "4.4",
    "block_number": "4.4",
    "knowledge_summary": "知识点：燃煤电厂、环保数据、电网接入技术规范、烟气脱硫、总则、系统、电力监控系统、安全防护要求\n\n摘要：本段内容讲述了燃煤电厂环保数据电网接入技术规范中关于烟气脱硫系统的总则要求，强调了系统必须符合电力监控系统安全防护的要求。",
    "page_content": "燃煤电厂环保数据电网接入技术规范 烟气脱硫 > 总则 > 系统应符合电力监控系统安全防护要求。",
    "children": [],
    "embedding": [],
    "metadata": {
      "original_level": 2
    }
  },
  "cb96e128-e9b8-47ac-8019-80a9e62eb991": {
    "id": "cb96e128-e9b8-47ac-8019-80a9e62eb991",
    "parent_id": "07930f97-c467-426a-bfc5-4ab1006bd9bf",
    "level": 1,
    "title": "5",
    "block_number": "5",
    "knowledge_summary": "知识点：燃煤电厂、环保数据、电网接入技术规范、烟气脱硫、运行条件\n摘要：该段落讲述了关于燃煤电厂在环保数据和电网接入技术规范方面，特别是烟气脱硫技术的运行条件的相关内容。\n\n【子节点综合】\n知识点: 燃煤电厂, 环保数据, 电网接入技术规范, 烟气脱硫, 运行条件, 机房环境系统, GB/T 9361, B级机房要求, 电源要求, AC 220V/50Hz 交流电源, 自动无扰切换, 交流不间断电源（UPS）, GB 7260.1 规定, UPS 容量, 实际额定负载, 备用时间\n\n摘要: 当前章节主要介绍了燃煤电厂在烟气脱硫过程中，机房环境系统需符合GB/T 9361标准中B级机房的要求，并对电源系统提出了具体要求，包括交流电源的配置、自动无扰切换功能以及UPS电源的容量和备用时间等，以确保环保数据的准确性和电网接入的稳定性。",
    "page_content": "燃煤电厂环保数据电网接入技术规范 烟气脱硫 > 运行条件",
    "children": [
      "d83c6fbf-7dc9-4cd6-a2dd-9181cf991714",
      "f01c4378-2549-4c14-ad84-75877784ddf4"
    ],
    "embedding": [],
    "metadata": {
      "original_level": 1,
      "child_knowledge": [
        {
          "title": "5.1",
          "summary": "知识点：燃煤电厂、环保数据、电网接入技术规范、烟气脱硫、运行条件、机房环境系统、GB/T 9361、B级机房要求\n\n摘要：本段内容讲述了燃煤电厂在烟气脱硫过程中，机房环境系统运行应符合GB/T 9361标准中B级机房的相关要求。"
        },
        {
          "title": "5.2",
          "summary": "知识点：燃煤电厂环保数据、电网接入技术规范、烟气脱硫、运行条件、电源要求、AC 220V/50Hz 交流电源、自动无扰切换、交流不间断电源（UPS）、GB 7260.1 规定、UPS 容量、实际额定负载、备用时间\n\n摘要：本段内容讲述了燃煤电厂环保数据电网接入技术规范中，关于烟气脱硫运行条件下的电源要求，包括主站和子站设备需配备的交流电源、自动无扰切换功能，以及UPS电源的具体要求，如容量和备用时间。"
        }
      ]
    }
  },
  "d83c6fbf-7dc9-4cd6-a2dd-9181cf991714": {
    "id": "d83c6fbf-7dc9-4cd6-a2dd-9181cf991714",
    "parent_id": "cb96e128-e9b8-47ac-8019-80a9e62eb991",
    "level": 2,
    "title": "5.1",
    "block_number": "5.1",
    "knowledge_summary": "知识点：燃煤电厂、环保数据、电网接入技术规范、烟气脱硫、运行条件、机房环境系统、GB/T 9361、B级机房要求\n\n摘要：本段内容讲述了燃煤电厂在烟气脱硫过程中，机房环境系统运行应符合GB/T 9361标准中B级机房的相关要求。",
    "page_content": "燃煤电厂环保数据电网接入技术规范 烟气脱硫 > 运行条件 > 机房环境系统运行的机房环境应符合GB/T 9361 中的 B 级机房的相关要求。",
    "children": [],
    "embedding": [],
    "metadata": {
      "original_level": 2
    }
  },
  "f01c4378-2549-4c14-ad84-75877784ddf4": {
    "id": "f01c4378-2549-4c14-ad84-75877784ddf4",
    "parent_id": "cb96e128-e9b8-47ac-8019-80a9e62eb991",
    "level": 2,
    "title": "5.2",
    "block_number": "5.2",
    "knowledge_summary": "知识点：燃煤电厂环保数据、电网接入技术规范、烟气脱硫、运行条件、电源要求、AC 220V/50Hz 交流电源、自动无扰切换、交流不间断电源（UPS）、GB 7260.1 规定、UPS 容量、实际额定负载、备用时间\n\n摘要：本段内容讲述了燃煤电厂环保数据电网接入技术规范中，关于烟气脱硫运行条件下的电源要求，包括主站和子站设备需配备的交流电源、自动无扰切换功能，以及UPS电源的具体要求，如容量和备用时间。",
    "page_content": "燃煤电厂环保数据电网接入技术规范 烟气脱硫 > 运行条件 > 电源电源应满足以下要求。a)主站和子站的设备均应配备两路 AC 220V/50Hz 交流电源供电，两路电源应具备自动无扰切换功能，其中至少一路应采用交流不间断电源（UPS）。UPS应符合 GB 7260.1 有关规定；b)UPS容量应不小于实际额定负载的 1.2 倍，备用时间宜不小于 2 小时。",
    "children": [],
    "embedding": [],
    "metadata": {
      "original_level": 2
    }
  },
  "b0c95d46-936a-4ade-a5d5-475d02b78eb2": {
    "id": "b0c95d46-936a-4ade-a5d5-475d02b78eb2",
    "parent_id": "07930f97-c467-426a-bfc5-4ab1006bd9bf",
    "level": 1,
    "title": "6",
    "block_number": "6",
    "knowledge_summary": "知识点：燃煤电厂、环保数据、电网接入技术规范、烟气脱硫、系统构成、功能\n\n摘要：本段讲述了关于燃煤电厂环保数据电网接入技术规范中的烟气脱硫系统，包括系统的构成和功能。\n\n【子节点综合】\n知识点: 燃煤电厂, 环保数据, 电网接入技术规范, 烟气脱硫, 系统构成, 功能, 实时监视, 统计报表\n摘要: [本章节详细阐述了燃煤电厂环保数据电网接入技术规范中烟气脱硫系统的构成和功能，包括系统的实时监视与统计报表生成，旨在提升燃煤电厂环保性能和数据管理效率。]",
    "page_content": "燃煤电厂环保数据电网接入技术规范 烟气脱硫 > 系统构成及功能",
    "children": [
      "72a8f4b1-dea4-477f-962e-30abd19ca037",
      "8e3b81a0-0724-4c22-a486-d8c1f85cb8d5"
    ],
    "embedding": [],
    "metadata": {
      "original_level": 1,
      "child_knowledge": [
        {
          "title": "6.1",
          "summary": "知识点：燃煤电厂、环保数据、电网接入技术规范、烟气脱硫、系统构成、功能\n摘要：本段内容讲述了关于燃煤电厂环保数据电网接入技术规范中烟气脱硫系统的构成及功能。"
        },
        {
          "title": "6.2",
          "summary": "知识点：燃煤电厂、环保数据、电网接入技术规范、烟气脱硫、系统构成、功能、实时监视、统计报表\n\n摘要：本段内容讲述了燃煤电厂在环保方面的技术规范，具体涉及烟气脱硫系统的构成和功能，以及如何进行实时监视和生成统计报表。"
        }
      ]
    }
  },
  "72a8f4b1-dea4-477f-962e-30abd19ca037": {
    "id": "72a8f4b1-dea4-477f-962e-30abd19ca037",
    "parent_id": "b0c95d46-936a-4ade-a5d5-475d02b78eb2",
    "level": 2,
    "title": "6.1",
    "block_number": "6.1",
    "knowledge_summary": "知识点：燃煤电厂、环保数据、电网接入技术规范、烟气脱硫、系统构成、功能\n摘要：本段内容讲述了关于燃煤电厂环保数据电网接入技术规范中烟气脱硫系统的构成及功能。\n\n【子节点综合】\n知识点: 燃煤电厂环保数据、电网接入技术规范、烟气脱硫、系统构成、功能、分布式系统、数据采集、存储、通信网络、冗余网络、安防设备、时间同步、运行状态监测、子站配置、通信网关、防火墙、远动通信、DCS、CEMS、脱硫监测、专线、调度数据网、交换机、路由器、网络连接线、DL∕T 1306-2013\n\n摘要: 当前章节主要阐述了燃煤电厂环保数据电网接入技术规范中烟气脱硫系统的整体构成和功能，涵盖了系统的基本结构、分布式系统架构、数据采集和存储、通信网络布局、冗余安全措施、安防设备和时间同步等方面，详细说明了系统构成的要求，包括通信网络、子站配置、专用通道以及相关设备和技术标准的应用。",
    "page_content": "燃煤电厂环保数据电网接入技术规范 烟气脱硫 > 系统构成及功能 > 系统构成",
    "children": [
      "4e3a7222-40cf-4a44-92ef-3b62f62c5fae",
      "be85846e-3d3e-410c-9b9f-c1bf0c5c44e2",
      "39742ca8-7d23-4566-8628-8a1fbba6015b",
      "18f4e01f-e390-43a3-921d-c60fa267dd3a"
    ],
    "embedding": [],
    "metadata": {
      "original_level": 2,
      "child_knowledge": [
        {
          "title": "6.1.1",
          "summary": "知识点：燃煤电厂环保数据、电网接入技术规范、烟气脱硫、系统构成及功能、系统构成、基本结构、主站、子站、通信网络、图1\n\n摘要：本段内容讲述了燃煤电厂环保数据电网接入技术规范中烟气脱硫系统的构成及功能，包括系统的基本结构，由主站、子站和二者之间的通信网络组成，并要求系统结构应符合图1所示。"
        },
        {
          "title": "6.1.2",
          "summary": "知识点：燃煤电厂、环保数据、电网接入技术规范、烟气脱硫、系统构成、功能、分布式系统结构、数据采集、计算、存储、镜像、监测信息发布、服务器功能、冗余网络、热备用方式、硬件防火墙、单向隔离装置、纵向认证加密、安防设备、时间同步源、运行状态监测\n\n摘要：本段讲述了燃煤电厂环保数据电网接入技术规范中烟气脱硫系统的构成及功能要求，包括分布式系统结构、数据采集、计算、存储、镜像、监测信息发布等功能，以及冗余网络、安防设备、时间同步源和运行状态监测等方面的技术要求。"
        },
        {
          "title": "6.1.3",
          "summary": "知识点：燃煤电厂、环保数据、电网接入技术规范、烟气脱硫、系统构成、功能、子站要求、通信网关、防火墙、专用设备、远动通信设备、DCS、CEMS、脱硫监测数据、硬接线、有线网络通信、缓存功能、断点续传、时间同步源、数据时间、自诊断、结果上传\n\n摘要：本段讲述了燃煤电厂环保数据电网接入技术规范中烟气脱硫系统的子站配置要求，包括通信网关和防火墙的配置、通信方式、数据采集传输功能、时间同步和数据自诊断上传等。"
        },
        {
          "title": "6.1.4",
          "summary": "知识点：燃煤电厂环保数据、电网接入技术规范、烟气脱硫、系统构成及功能、系统构成、通信网络、专线、调度数据网、DL∕T 1306-2013、专用通道、交换机、路由器、网络连接线\n摘要：本段内容讲述了燃煤电厂环保数据在电网接入技术规范中关于烟气脱硫系统的构成和功能，特别指出通信网络应使用专线或调度数据网等专用通道，并列举了所需的设备如交换机、路由器和网络连接线，同时提到了相关指南标准DL∕T 1306-2013。"
        }
      ]
    }
  },
  "4e3a7222-40cf-4a44-92ef-3b62f62c5fae": {
    "id": "4e3a7222-40cf-4a44-92ef-3b62f62c5fae",
    "parent_id": "72a8f4b1-dea4-477f-962e-30abd19ca037",
    "level": 3,
    "title": "6.1.1",
    "block_number": "6.1.1",
    "knowledge_summary": "知识点：燃煤电厂环保数据、电网接入技术规范、烟气脱硫、系统构成及功能、系统构成、基本结构、主站、子站、通信网络、图1\n\n摘要：本段内容讲述了燃煤电厂环保数据电网接入技术规范中烟气脱硫系统的构成及功能，包括系统的基本结构，由主站、子站和二者之间的通信网络组成，并要求系统结构应符合图1所示。",
    "page_content": "燃煤电厂环保数据电网接入技术规范 烟气脱硫 > 系统构成及功能 > 系统构成 > 基本结构系统由主站、子站以及二者之间的通信网络组成，系统结构应与图1 相符合。",
    "children": [],
    "embedding": [],
    "metadata": {
      "original_level": 3
    }
  },
  "be85846e-3d3e-410c-9b9f-c1bf0c5c44e2": {
    "id": "be85846e-3d3e-410c-9b9f-c1bf0c5c44e2",
    "parent_id": "72a8f4b1-dea4-477f-962e-30abd19ca037",
    "level": 3,
    "title": "6.1.2",
    "block_number": "6.1.2",
    "knowledge_summary": "知识点：燃煤电厂、环保数据、电网接入技术规范、烟气脱硫、系统构成、功能、分布式系统结构、数据采集、计算、存储、镜像、监测信息发布、服务器功能、冗余网络、热备用方式、硬件防火墙、单向隔离装置、纵向认证加密、安防设备、时间同步源、运行状态监测\n\n摘要：本段讲述了燃煤电厂环保数据电网接入技术规范中烟气脱硫系统的构成及功能要求，包括分布式系统结构、数据采集、计算、存储、镜像、监测信息发布等功能，以及冗余网络、安防设备、时间同步源和运行状态监测等方面的技术要求。",
    "page_content": "燃煤电厂环保数据电网接入技术规范 烟气脱硫 > 系统构成及功能 > 系统构成 > 主站主站应满足以下要求。a)采用分布式系统结构，应配置数据采集、计算、存储、镜像及监测信息发布的服务b)数据采集服务器具备子站数据采集和汇聚功能；c)数据库服务器具备实时和历史数据存储功能，实现对实时数据、历史数据的快速查器；询；d)计算服务器具备数据的统计报表功能；e)工作站具备连接服务器并进行系统配置和调试的功能；f)镜像服务器具备生产控制大区至管理信息大区的实时、历史数据镜像功能；g)发布服务器具备网站信息发布功能；h)采用冗余网络和热备用方式运行，包括各种服务器、通信装置、磁盘阵列；根据GB/T36572-2018 配置硬件防火墙、单向隔离装置、纵向认证加密等安防设备；DL/TXXXXX－20XXi)接收时间同步源的对时，数据时间以数据源为准；j)定时下发对时报文给各子站；k)对子站的运行状态进行在线监测。",
    "children": [],
    "embedding": [],
    "metadata": {
      "original_level": 3
    }
  },
  "39742ca8-7d23-4566-8628-8a1fbba6015b": {
    "id": "39742ca8-7d23-4566-8628-8a1fbba6015b",
    "parent_id": "72a8f4b1-dea4-477f-962e-30abd19ca037",
    "level": 3,
    "title": "6.1.3",
    "block_number": "6.1.3",
    "knowledge_summary": "知识点：燃煤电厂、环保数据、电网接入技术规范、烟气脱硫、系统构成、功能、子站要求、通信网关、防火墙、专用设备、远动通信设备、DCS、CEMS、脱硫监测数据、硬接线、有线网络通信、缓存功能、断点续传、时间同步源、数据时间、自诊断、结果上传\n\n摘要：本段讲述了燃煤电厂环保数据电网接入技术规范中烟气脱硫系统的子站配置要求，包括通信网关和防火墙的配置、通信方式、数据采集传输功能、时间同步和数据自诊断上传等。",
    "page_content": "燃煤电厂环保数据电网接入技术规范 烟气脱硫 > 系统构成及功能 > 系统构成 > 子站子站应满足以下要求。a)子站配置通信网关以及防火墙；b)通信网关配置专用设备或使用现有远动通信设备；c)从 DCS、CEMS 等系统采集脱硫监测数据时，采用硬接线或有线网络通信方式；d)数据采集和传输具备缓存功能，支持断点续传；e)接收时间同步源的对时，数据时间以数据源为准；f)具备子站状态自诊断及结果上传主站功能。",
    "children": [],
    "embedding": [],
    "metadata": {
      "original_level": 3
    }
  },
  "18f4e01f-e390-43a3-921d-c60fa267dd3a": {
    "id": "18f4e01f-e390-43a3-921d-c60fa267dd3a",
    "parent_id": "72a8f4b1-dea4-477f-962e-30abd19ca037",
    "level": 3,
    "title": "6.1.4",
    "block_number": "6.1.4",
    "knowledge_summary": "知识点：燃煤电厂环保数据、电网接入技术规范、烟气脱硫、系统构成及功能、系统构成、通信网络、专线、调度数据网、DL∕T 1306-2013、专用通道、交换机、路由器、网络连接线\n摘要：本段内容讲述了燃煤电厂环保数据在电网接入技术规范中关于烟气脱硫系统的构成和功能，特别指出通信网络应使用专线或调度数据网等专用通道，并列举了所需的设备如交换机、路由器和网络连接线，同时提到了相关指南标准DL∕T 1306-2013。",
    "page_content": "燃煤电厂环保数据电网接入技术规范 烟气脱硫 > 系统构成及功能 > 系统构成 > 通信网络通信网络应采用专线或调度数据网（进一步指南见DL∕T 1306-2013）等专用通道，包括交换机、路由器、网络连接线等设备。图1 系统结构示意图",
    "children": [],
    "embedding": [],
    "metadata": {
      "original_level": 3
    }
  },
  "8e3b81a0-0724-4c22-a486-d8c1f85cb8d5": {
    "id": "8e3b81a0-0724-4c22-a486-d8c1f85cb8d5",
    "parent_id": "b0c95d46-936a-4ade-a5d5-475d02b78eb2",
    "level": 2,
    "title": "6.2",
    "block_number": "6.2",
    "knowledge_summary": "知识点：燃煤电厂、环保数据、电网接入技术规范、烟气脱硫、系统构成、功能、实时监视、统计报表\n\n摘要：本段内容讲述了燃煤电厂在环保方面的技术规范，具体涉及烟气脱硫系统的构成和功能，以及如何进行实时监视和生成统计报表。\n\n【子节点综合】\n知识点: 燃煤电厂、环保数据、电网接入技术规范、烟气脱硫、系统构成、功能、实时监视、统计报表、历史回放、机组发电功率、二氧化硫排放浓度、小时排放浓度、排放超标信息、实时曲线、历史曲线、告警信息、历史数据库、分类检索、报表功能、日统计报表、月统计报表、年统计报表、趋势分析、数据对比、查询结果生成报表、导出格式\n\n摘要: 本章节详细介绍了燃煤电厂环保数据电网接入技术规范中烟气脱硫系统的实时监视和统计报表功能。内容包括系统的构成与功能，如实时监视画面、曲线显示、告警信息存储与检索，以及统计报表的生成、趋势分析、数据对比和导出格式等，旨在确保烟气脱硫过程的环保数据准确性和可追溯性。",
    "page_content": "燃煤电厂环保数据电网接入技术规范 烟气脱硫 > 系统构成及功能 > 实时监视及统计报表",
    "children": [
      "d5a0c81f-d7c7-4709-9fff-4cd0e67f0d33",
      "c2f75b04-72a3-4aab-a399-c379193609f7"
    ],
    "embedding": [],
    "metadata": {
      "original_level": 2,
      "child_knowledge": [
        {
          "title": "6.2.1",
          "summary": "知识点：燃煤电厂、环保数据、电网接入技术规范、烟气脱硫、系统构成、功能、实时监视、统计报表、历史回放功能、机组发电功率、二氧化硫排放浓度、小时排放浓度、排放超标信息、实时曲线、历史曲线、告警信息、历史数据库、分类检索。\n\n摘要：本段内容讲述了燃煤电厂环保数据电网接入技术规范中烟气脱硫系统的实时监视功能，包括监视画面、实时曲线和历史曲线的显示，以及告警信息的存储和分类检索。"
        },
        {
          "title": "6.2.2",
          "summary": "知识点：燃煤电厂、环保数据、电网接入技术规范、烟气脱硫、系统构成、功能、实时监视、统计报表、报表功能、日、月、年统计报表、趋势分析、数据对比、查询结果生成报表、导出格式.doc、.xls、.pdf\n\n摘要：本段内容讲述了燃煤电厂环保数据电网接入技术规范中烟气脱硫系统的构成与功能，特别强调了统计报表的功能要求，包括提供不同时间周期的报表、支持趋势分析和数据对比查询结果生成报表，以及导出为常用办公软件格式的能力。"
        }
      ]
    }
  },
  "d5a0c81f-d7c7-4709-9fff-4cd0e67f0d33": {
    "id": "d5a0c81f-d7c7-4709-9fff-4cd0e67f0d33",
    "parent_id": "8e3b81a0-0724-4c22-a486-d8c1f85cb8d5",
    "level": 3,
    "title": "6.2.1",
    "block_number": "6.2.1",
    "knowledge_summary": "知识点：燃煤电厂、环保数据、电网接入技术规范、烟气脱硫、系统构成、功能、实时监视、统计报表、历史回放功能、机组发电功率、二氧化硫排放浓度、小时排放浓度、排放超标信息、实时曲线、历史曲线、告警信息、历史数据库、分类检索。\n\n摘要：本段内容讲述了燃煤电厂环保数据电网接入技术规范中烟气脱硫系统的实时监视功能，包括监视画面、实时曲线和历史曲线的显示，以及告警信息的存储和分类检索。",
    "page_content": "燃煤电厂环保数据电网接入技术规范 烟气脱硫 > 系统构成及功能 > 实时监视及统计报表 > 实时监视实时监视功能应满足如下要求。DL/TXXXXX－20XXa)监视画面包括机组发电功率、二氧化硫实时排放浓度及小时排放浓度、排放超标信息等重要参数信息，具有历史回放功能；b)显示各监测数据的实时曲线和历史曲线；c)告警信息存储到历史数据库中，可分类检索。",
    "children": [],
    "embedding": [],
    "metadata": {
      "original_level": 3
    }
  },
  "c2f75b04-72a3-4aab-a399-c379193609f7": {
    "id": "c2f75b04-72a3-4aab-a399-c379193609f7",
    "parent_id": "8e3b81a0-0724-4c22-a486-d8c1f85cb8d5",
    "level": 3,
    "title": "6.2.2",
    "block_number": "6.2.2",
    "knowledge_summary": "知识点：燃煤电厂、环保数据、电网接入技术规范、烟气脱硫、系统构成、功能、实时监视、统计报表、报表功能、日、月、年统计报表、趋势分析、数据对比、查询结果生成报表、导出格式.doc、.xls、.pdf\n\n摘要：本段内容讲述了燃煤电厂环保数据电网接入技术规范中烟气脱硫系统的构成与功能，特别强调了统计报表的功能要求，包括提供不同时间周期的报表、支持趋势分析和数据对比查询结果生成报表，以及导出为常用办公软件格式的能力。",
    "page_content": "燃煤电厂环保数据电网接入技术规范 烟气脱硫 > 系统构成及功能 > 实时监视及统计报表 > 统计报表报表功能应满足如下要求。a)提供日、月、年等不同时间周期的统计报表；b)趋势分析、数据对比等查询结果生成报表；c)支持以.doc、.xls、.pdf 等常用办公软件格式导出。",
    "children": [],
    "embedding": [],
    "metadata": {
      "original_level": 3
    }
  },
  "fa67dd51-4741-4981-80b9-1354dff2a7ef": {
    "id": "fa67dd51-4741-4981-80b9-1354dff2a7ef",
    "parent_id": "07930f97-c467-426a-bfc5-4ab1006bd9bf",
    "level": 1,
    "title": "7",
    "block_number": "7",
    "knowledge_summary": "知识点：燃煤电厂、环保数据、电网接入技术规范、烟气脱硫、数据采集、数据处理\n摘要：该段落讲述了关于燃煤电厂的环保数据，包括电网接入技术规范中的烟气脱硫环节，以及数据采集和处理的有关内容。\n\n【子节点综合】\n知识点: 燃煤电厂, 环保数据, 电网接入技术规范, 烟气脱硫, 数据采集, 数据处理, 数据校验, 主站, 子站上传, 数据有效性判断, 异常数据处理\n\n摘要: 本章节主要探讨了燃煤电厂在环保数据电网接入技术规范中的具体应用，尤其是针对烟气脱硫过程中的数据采集与处理方法，包括数据校验、主站对子站上传数据的有效性判断和异常数据处理等技术要求。",
    "page_content": "燃煤电厂环保数据电网接入技术规范 烟气脱硫 > 数据采集和处理",
    "children": [
      "97b3133b-ffff-451e-9d78-69096ad50a20",
      "31db533c-8ee0-4942-a3b0-b2218a522551"
    ],
    "embedding": [],
    "metadata": {
      "original_level": 1,
      "child_knowledge": [
        {
          "title": "7.1",
          "summary": "知识点：燃煤电厂、环保数据、电网接入技术规范、烟气脱硫、数据采集、数据处理\n\n摘要：本段内容讲述了关于燃煤电厂环保数据在电网接入技术规范中的应用，特别是烟气脱硫过程中的数据采集和处理方法。"
        },
        {
          "title": "7.2",
          "summary": "知识点：燃煤电厂、环保数据、电网接入技术规范、烟气脱硫、数据采集和处理、数据校验、主站、子站上传、数据有效性判断、异常数据处理\n摘要：本段落主要讲述了燃煤电厂在环保数据电网接入技术规范中，对于烟气脱硫过程中的数据采集和处理，特别是数据校验环节，主站如何对子站上传的数据进行有效性判断以及异常数据处理的相关技术要求。"
        }
      ]
    }
  },
  "97b3133b-ffff-451e-9d78-69096ad50a20": {
    "id": "97b3133b-ffff-451e-9d78-69096ad50a20",
    "parent_id": "fa67dd51-4741-4981-80b9-1354dff2a7ef",
    "level": 2,
    "title": "7.1",
    "block_number": "7.1",
    "knowledge_summary": "知识点：燃煤电厂、环保数据、电网接入技术规范、烟气脱硫、数据采集、数据处理\n\n摘要：本段内容讲述了关于燃煤电厂环保数据在电网接入技术规范中的应用，特别是烟气脱硫过程中的数据采集和处理方法。\n\n【子节点综合】\n知识点: 燃煤电厂, 环保数据, 电网接入技术规范, 烟气脱硫, 数据采集, 数据处理, 采集范围, 子站采集, 测点, 附录A, 典型工艺, 附录B, 数据来源, CEMS, DCS, 通信方式, 硬接线, 有线网络方式, 通信协议, OPC, Modbus, 机组上网电量, 电能计量主站系统, 数据传输, 通信网络, 主站, 子站, DL/T634.5101, DL/T634.5104, 通信规约, 数据存储, 历史数据库, 原始数据, 统计, 综合处理, 存储格式, HJ 76-2017 附录 B.1\n\n摘要: 本章节详细阐述了燃煤电厂环保数据在电网接入技术规范中的具体应用，涉及烟气脱硫过程中数据采集与处理的方法和规范，包括数据采集范围、子站测点要求、数据来源、采集与传输方式、通信协议、数据存储和格式要求等，旨在确保环保数据的准确性和完整性，满足电网接入的技术需求。",
    "page_content": "燃煤电厂环保数据电网接入技术规范 烟气脱硫 > 数据采集和处理 > 数据采集",
    "children": [
      "848a0946-11fa-442e-b1d6-b3a53fa699e0",
      "3751c88a-9aa9-4d45-b294-d41a775d0eb3",
      "b39adbbb-cbef-4f61-8375-da67a5429c9a",
      "6394b5da-9b5d-4dd0-85d4-4b75a1ee7baa"
    ],
    "embedding": [],
    "metadata": {
      "original_level": 2,
      "child_knowledge": [
        {
          "title": "7.1.1",
          "summary": "知识点：燃煤电厂、环保数据、电网接入技术规范、烟气脱硫、数据采集、处理、采集范围、子站采集、测点、附录A、典型工艺、附录B\n\n摘要：本段内容讲述了燃煤电厂环保数据在电网接入技术规范中的应用，具体包括烟气脱硫过程中的数据采集和处理方法，要求子站采集测点需符合附录A的规定，并采用典型工艺进行采集测点，详见附录B。"
        },
        {
          "title": "7.1.2",
          "summary": "知识点：燃煤电厂环保数据、电网接入技术规范、烟气脱硫、数据采集和处理、数据来源、CEMS、DCS、子站、硬接线、有线网络方式、通信协议、OPC、Modbus、机组上网电量、电能计量主站系统\n\n摘要：本段讲述了燃煤电厂环保数据在烟气脱硫过程中的数据采集和处理规范，包括数据来源的要求，如监测数据应包括CEMS、DCS等，在子站汇总后统一上传，以及子站与CEMS、DCS的通信方式和通信协议，以及机组上网电量的获取方式。"
        },
        {
          "title": "7.1.3",
          "summary": "知识点：燃煤电厂、环保数据、电网接入技术规范、烟气脱硫、数据采集、数据处理、数据传输、通信网络、主站、子站、DL/T634.5101、DL/T634.5104、通信规约\n\n摘要：本段内容讲述了燃煤电厂环保数据在电网接入技术规范中的数据传输要求，包括数据采集、传输、存储、计算、汇总以及使用特定通信规约进行数据传输的相关细节。"
        },
        {
          "title": "7.1.4",
          "summary": "知识点：燃煤电厂、环保数据、电网接入技术规范、烟气脱硫、数据采集、数据处理、数据存储、历史数据库、原始数据、统计、综合处理、存储格式、HJ 76-2017 附录 B.1\n\n摘要：本段内容讲述了燃煤电厂在环保数据电网接入技术规范中关于烟气脱硫的数据采集和处理要求，包括将机组运行信息存储到历史数据库，支持原始数据的统计及综合处理，以及存储格式需符合HJ 76-2017附录B.1的要求。"
        }
      ]
    }
  },
  "848a0946-11fa-442e-b1d6-b3a53fa699e0": {
    "id": "848a0946-11fa-442e-b1d6-b3a53fa699e0",
    "parent_id": "97b3133b-ffff-451e-9d78-69096ad50a20",
    "level": 3,
    "title": "7.1.1",
    "block_number": "7.1.1",
    "knowledge_summary": "知识点：燃煤电厂、环保数据、电网接入技术规范、烟气脱硫、数据采集、处理、采集范围、子站采集、测点、附录A、典型工艺、附录B\n\n摘要：本段内容讲述了燃煤电厂环保数据在电网接入技术规范中的应用，具体包括烟气脱硫过程中的数据采集和处理方法，要求子站采集测点需符合附录A的规定，并采用典型工艺进行采集测点，详见附录B。",
    "page_content": "燃煤电厂环保数据电网接入技术规范 烟气脱硫 > 数据采集和处理 > 数据采集 > 采集范围子站采集测点应符合附录A 的要求。采用典型工艺采集测点参见附录 B。",
    "children": [],
    "embedding": [],
    "metadata": {
      "original_level": 3
    }
  },
  "3751c88a-9aa9-4d45-b294-d41a775d0eb3": {
    "id": "3751c88a-9aa9-4d45-b294-d41a775d0eb3",
    "parent_id": "97b3133b-ffff-451e-9d78-69096ad50a20",
    "level": 3,
    "title": "7.1.2",
    "block_number": "7.1.2",
    "knowledge_summary": "知识点：燃煤电厂环保数据、电网接入技术规范、烟气脱硫、数据采集和处理、数据来源、CEMS、DCS、子站、硬接线、有线网络方式、通信协议、OPC、Modbus、机组上网电量、电能计量主站系统\n\n摘要：本段讲述了燃煤电厂环保数据在烟气脱硫过程中的数据采集和处理规范，包括数据来源的要求，如监测数据应包括CEMS、DCS等，在子站汇总后统一上传，以及子站与CEMS、DCS的通信方式和通信协议，以及机组上网电量的获取方式。",
    "page_content": "燃煤电厂环保数据电网接入技术规范 烟气脱硫 > 数据采集和处理 > 数据采集 > 数据来源数据来源应满足如下要求。a)监测数据来源包括 CEMS、DCS 等，在子站进行汇总后统一上传；b)子站与 CEMS 通信采用硬接线或有线网络方式；c)子站与 DCS 采用有线网络通信方式，通信协议使用 OPC 或 Modbus；d)机组上网电量从电能计量主站系统获取。",
    "children": [],
    "embedding": [],
    "metadata": {
      "original_level": 3
    }
  },
  "b39adbbb-cbef-4f61-8375-da67a5429c9a": {
    "id": "b39adbbb-cbef-4f61-8375-da67a5429c9a",
    "parent_id": "97b3133b-ffff-451e-9d78-69096ad50a20",
    "level": 3,
    "title": "7.1.3",
    "block_number": "7.1.3",
    "knowledge_summary": "知识点：燃煤电厂、环保数据、电网接入技术规范、烟气脱硫、数据采集、数据处理、数据传输、通信网络、主站、子站、DL/T634.5101、DL/T634.5104、通信规约\n\n摘要：本段内容讲述了燃煤电厂环保数据在电网接入技术规范中的数据传输要求，包括数据采集、传输、存储、计算、汇总以及使用特定通信规约进行数据传输的相关细节。",
    "page_content": "燃煤电厂环保数据电网接入技术规范 烟气脱硫 > 数据采集和处理 > 数据采集 > 数据传输数据传输应满足如下要求。a)子站完成数据的采集，经由通信网络上传至主站，在主站完成数据的存储、计算、汇总后，经隔离装置在管理信息大区完成数据镜像和信息发布；b)主站和子站之间宜使用 DL/T634.5101、DL/T634.5104 通信规约进行数据传输。",
    "children": [],
    "embedding": [],
    "metadata": {
      "original_level": 3
    }
  },
  "6394b5da-9b5d-4dd0-85d4-4b75a1ee7baa": {
    "id": "6394b5da-9b5d-4dd0-85d4-4b75a1ee7baa",
    "parent_id": "97b3133b-ffff-451e-9d78-69096ad50a20",
    "level": 3,
    "title": "7.1.4",
    "block_number": "7.1.4",
    "knowledge_summary": "知识点：燃煤电厂、环保数据、电网接入技术规范、烟气脱硫、数据采集、数据处理、数据存储、历史数据库、原始数据、统计、综合处理、存储格式、HJ 76-2017 附录 B.1\n\n摘要：本段内容讲述了燃煤电厂在环保数据电网接入技术规范中关于烟气脱硫的数据采集和处理要求，包括将机组运行信息存储到历史数据库，支持原始数据的统计及综合处理，以及存储格式需符合HJ 76-2017附录B.1的要求。",
    "page_content": "燃煤电厂环保数据电网接入技术规范 烟气脱硫 > 数据采集和处理 > 数据采集 > 数据存储数据存储应满足如下要求。a)主站将子站采集到的机组各种运行信息存储到历史数据库；b)支持对原始采集数据的统计及综合处理；c)存储格式符合 HJ 76-2017 附录 B.1 的要求。",
    "children": [],
    "embedding": [],
    "metadata": {
      "original_level": 3
    }
  },
  "31db533c-8ee0-4942-a3b0-b2218a522551": {
    "id": "31db533c-8ee0-4942-a3b0-b2218a522551",
    "parent_id": "fa67dd51-4741-4981-80b9-1354dff2a7ef",
    "level": 2,
    "title": "7.2",
    "block_number": "7.2",
    "knowledge_summary": "知识点：燃煤电厂、环保数据、电网接入技术规范、烟气脱硫、数据采集和处理、数据校验、主站、子站上传、数据有效性判断、异常数据处理\n摘要：本段落主要讲述了燃煤电厂在环保数据电网接入技术规范中，对于烟气脱硫过程中的数据采集和处理，特别是数据校验环节，主站如何对子站上传的数据进行有效性判断以及异常数据处理的相关技术要求。",
    "page_content": "燃煤电厂环保数据电网接入技术规范 烟气脱硫 > 数据采集和处理 > 数据校验主站应对子站上传的数据进行有效性判断，对异常数据进行处理。",
    "children": [],
    "embedding": [],
    "metadata": {
      "original_level": 2
    }
  },
  "856a56e3-b2aa-40dc-a58a-591c750b0ec4": {
    "id": "856a56e3-b2aa-40dc-a58a-591c750b0ec4",
    "parent_id": "07930f97-c467-426a-bfc5-4ab1006bd9bf",
    "level": 1,
    "title": "8",
    "block_number": "8",
    "knowledge_summary": "知识点：燃煤电厂、环保数据、电网接入技术规范、烟气脱硫、性能指标\n\n摘要：本段内容讲述了关于燃煤电厂环保数据、电网接入技术规范以及烟气脱硫的相关性能指标。\n\n【子节点综合】\n知识点: 燃煤电厂、环保数据、电网接入技术规范、烟气脱硫、性能指标、可用性、主站、子站、可用率、DL/T 924-2016、容量要求、存储容量、接入要求、历史数据存储时间、实时性、系统响应时间、双机热备、切换时间、监视画面调用时间、报表、系统资源、服务器、工作站CPU、平均负荷率、网络通信负荷率\n\n摘要: 本章节详细阐述了燃煤电厂在环保数据电网接入技术规范中关于烟气脱硫的性能指标要求，涵盖了可用性、容量、实时性、系统资源等多个方面。具体包括主站和子站的可用率需符合DL/T 924-2016标准，存储容量和接入要求应满足规范，实时性指标如系统响应时间、切换时间等需满足HJ75-2017等标准，同时，系统资源如服务器和工作站CPU的平均负荷率及网络通信负荷率也应满足DL/T 924-2016的要求。",
    "page_content": "燃煤电厂环保数据电网接入技术规范 烟气脱硫 > 性能指标",
    "children": [
      "d502a72a-94db-48cd-8f98-732d822a023e",
      "4f5704cb-69ec-4188-888f-e32d7f4b00b0",
      "6d495ff2-4a67-4e2c-ab2e-ab61424ffb69",
      "6efd0c87-6adc-4d40-a453-f5a1cc1c386c"
    ],
    "embedding": [],
    "metadata": {
      "original_level": 1,
      "child_knowledge": [
        {
          "title": "8.1",
          "summary": "知识点：燃煤电厂、环保数据、电网接入技术规范、烟气脱硫、性能指标、可用性、主站、子站、可用率、DL/T 924-2016、4.10要求、DL/TXXXXX－20XX\n\n摘要：本段内容讲述了燃煤电厂在环保数据电网接入技术规范中关于烟气脱硫性能指标的要求，包括主站和子站的可用率应满足DL/T 924-2016标准第4.10条的要求，并提及了未来可能的新标准DL/TXXXXX－20XX。"
        },
        {
          "title": "8.2",
          "summary": "知识点：燃煤电厂环保数据、电网接入技术规范、烟气脱硫、性能指标、容量要求、主站接入数据点、存储容量、接入要求、历史数据存储时间、DL/T 924-2016、6.1.7要求。\n\n摘要：本段内容讲述了燃煤电厂环保数据在电网接入技术规范中的存储要求，包括主站接入数据点的存储容量需要满足接入要求并预留裕量，以及历史数据存储时间应符合DL/T 924-2016标准中6.1.7的要求。"
        },
        {
          "title": "8.3",
          "summary": "知识点：燃煤电厂、环保数据、电网接入技术规范、烟气脱硫、性能指标、实时性、系统响应时间、HJ75-2017、双机热备、切换时间、监视画面调用时间、报表\n\n摘要：本段讲述了燃煤电厂环保数据电网接入技术规范中关于烟气脱硫性能指标的实时性要求，包括系统响应时间需满足HJ75-2017标准，主备设备宜采用双机热备方式，切换时间不大于30秒，监视画面调用时间不大于2秒，报表生成时间不大于5秒。"
        },
        {
          "title": "8.4",
          "summary": "知识点：燃煤电厂环保数据、电网接入技术规范、烟气脱硫、性能指标、系统资源、服务器、工作站CPU、平均负荷率、网络通信负荷率、DL/T 924-2016、7.1.3要求\n\n摘要：本段内容讲述了燃煤电厂环保数据电网接入技术规范中关于烟气脱硫的性能指标要求，包括系统资源服务器和工作站CPU的平均负荷率及网络通信负荷率，需满足DL/T 924-2016标准的7.1.3要求。"
        }
      ]
    }
  },
  "d502a72a-94db-48cd-8f98-732d822a023e": {
    "id": "d502a72a-94db-48cd-8f98-732d822a023e",
    "parent_id": "856a56e3-b2aa-40dc-a58a-591c750b0ec4",
    "level": 2,
    "title": "8.1",
    "block_number": "8.1",
    "knowledge_summary": "知识点：燃煤电厂、环保数据、电网接入技术规范、烟气脱硫、性能指标、可用性、主站、子站、可用率、DL/T 924-2016、4.10要求、DL/TXXXXX－20XX\n\n摘要：本段内容讲述了燃煤电厂在环保数据电网接入技术规范中关于烟气脱硫性能指标的要求，包括主站和子站的可用率应满足DL/T 924-2016标准第4.10条的要求，并提及了未来可能的新标准DL/TXXXXX－20XX。",
    "page_content": "燃煤电厂环保数据电网接入技术规范 烟气脱硫 > 性能指标 > 可用性主站和子站的可用率应满足DL/T 924-2016,4.10 要求。DL/TXXXXX－20XX",
    "children": [],
    "embedding": [],
    "metadata": {
      "original_level": 2
    }
  },
  "4f5704cb-69ec-4188-888f-e32d7f4b00b0": {
    "id": "4f5704cb-69ec-4188-888f-e32d7f4b00b0",
    "parent_id": "856a56e3-b2aa-40dc-a58a-591c750b0ec4",
    "level": 2,
    "title": "8.2",
    "block_number": "8.2",
    "knowledge_summary": "知识点：燃煤电厂环保数据、电网接入技术规范、烟气脱硫、性能指标、容量要求、主站接入数据点、存储容量、接入要求、历史数据存储时间、DL/T 924-2016、6.1.7要求。\n\n摘要：本段内容讲述了燃煤电厂环保数据在电网接入技术规范中的存储要求，包括主站接入数据点的存储容量需要满足接入要求并预留裕量，以及历史数据存储时间应符合DL/T 924-2016标准中6.1.7的要求。",
    "page_content": "燃煤电厂环保数据电网接入技术规范 烟气脱硫 > 性能指标 > 容量要求主站接入数据点的存储容量应满足如下要求。a)测点容量满足接入要求，并预留一定的裕量；b)历史数据存储时间应满足 DL/T 924-2016,6.1.7 要求。",
    "children": [],
    "embedding": [],
    "metadata": {
      "original_level": 2
    }
  },
  "6d495ff2-4a67-4e2c-ab2e-ab61424ffb69": {
    "id": "6d495ff2-4a67-4e2c-ab2e-ab61424ffb69",
    "parent_id": "856a56e3-b2aa-40dc-a58a-591c750b0ec4",
    "level": 2,
    "title": "8.3",
    "block_number": "8.3",
    "knowledge_summary": "知识点：燃煤电厂、环保数据、电网接入技术规范、烟气脱硫、性能指标、实时性、系统响应时间、HJ75-2017、双机热备、切换时间、监视画面调用时间、报表\n\n摘要：本段讲述了燃煤电厂环保数据电网接入技术规范中关于烟气脱硫性能指标的实时性要求，包括系统响应时间需满足HJ75-2017标准，主备设备宜采用双机热备方式，切换时间不大于30秒，监视画面调用时间不大于2秒，报表生成时间不大于5秒。",
    "page_content": "燃煤电厂环保数据电网接入技术规范 烟气脱硫 > 性能指标 > 实时性实时性应满足如下要求。a)系统响应时间应满足 HJ75-2017,6.2.1.2 要求；b)主备设备宜采用双机热备方式，切换时间不大于 30 秒；c)监视画面调用时间不大于 2 秒，报表不大于 5 秒。",
    "children": [],
    "embedding": [],
    "metadata": {
      "original_level": 2
    }
  },
  "6efd0c87-6adc-4d40-a453-f5a1cc1c386c": {
    "id": "6efd0c87-6adc-4d40-a453-f5a1cc1c386c",
    "parent_id": "856a56e3-b2aa-40dc-a58a-591c750b0ec4",
    "level": 2,
    "title": "8.4",
    "block_number": "8.4",
    "knowledge_summary": "知识点：燃煤电厂环保数据、电网接入技术规范、烟气脱硫、性能指标、系统资源、服务器、工作站CPU、平均负荷率、网络通信负荷率、DL/T 924-2016、7.1.3要求\n\n摘要：本段内容讲述了燃煤电厂环保数据电网接入技术规范中关于烟气脱硫的性能指标要求，包括系统资源服务器和工作站CPU的平均负荷率及网络通信负荷率，需满足DL/T 924-2016标准的7.1.3要求。",
    "page_content": "燃煤电厂环保数据电网接入技术规范 烟气脱硫 > 性能指标 > 系统资源服务器、工作站CPU 平均负荷率及网络通信负荷率应满足 DL/T 924-2016,7.1.3 要求。",
    "children": [],
    "embedding": [],
    "metadata": {
      "original_level": 2
    }
  }
}