{
  "f4ad28eb-3dc6-4833-a62b-c49d2dd9e491": {
    "id": "f4ad28eb-3dc6-4833-a62b-c49d2dd9e491",
    "parent_id": null,
    "level": 0,
    "title": "84801",
    "block_number": "",
    "knowledge_summary": "知识点: 变压器振荡型操作冲击感应耐压试验、试验原理、试验条件、试验方法、结果判断、试验记录、110kV～750kV电压等级、油浸式电力变压器、试验记录内容、规范性引用文件、术语和定义、试验装置、试验接线、试验方法、结果判断标准\n\n摘要: 本章节详细介绍了变压器振荡型操作冲击感应耐压试验的相关知识，包括试验原理、条件、方法、结果判断、记录格式等，适用于110kV～750kV电压等级的油浸式电力变压器。章节内容涵盖了试验记录应包含的信息、规范性引用的文件标准、术语和定义、试验装置、接线要求以及结果判断标准，旨在确保试验的准确性和安全性。",
    "page_content": "",
    "children": [
      "0aef81f4-93cd-4d45-b1e3-cc42b62e0670",
      "6be5faaa-3b9d-4661-b10b-f7aa3826734c",
      "4c7eafdf-a3f0-41e0-9f66-3be7c810e534",
      "0ebb8e1a-444c-4c4c-b9e8-5b7da82a9dcd",
      "90f98a93-810a-44ac-9ca6-02be4955865f",
      "4a1efec3-5c40-49b5-90a9-aaa3027ccf8a",
      "bdf655ea-0632-4b98-8514-2e269df0503e",
      "032fc5d4-80d7-4c83-b97d-e5419e071ceb",
      "c2c75d3f-5a32-4e84-850d-4c7d3a654653",
      "9b8b0a35-ad79-4ec5-add7-85287ea573b5"
    ],
    "embedding": [],
    "metadata": {
      "child_knowledge": [
        {
          "title": "1",
          "summary": "知识点：变压器振荡型操作冲击感应耐压试验、试验原理、试验条件、试验方法、结果判断、试验记录、110kV～750kV电压等级、油浸式电力变压器\n\n摘要：本文件规定了变压器振荡型操作冲击感应耐压试验的相关要求，包括试验原理、条件、方法、结果判断及记录等，适用于110kV～750kV电压等级的油浸式电力变压器，其他电压等级变压器可参考使用。"
        },
        {
          "title": "10",
          "summary": "知识点：变压器振荡型操作冲击感应耐压试验、试验记录、振荡操作冲击试验记录、被试变压器型号、制造厂家、出厂编号、出厂日期、试验场地温湿度、试验工作地点、日期、绕组冲击试验情况、振荡冲击发生器配置参数、被试绕组电压波形、波头时间、波尾时间、振荡频率、电压幅值、波形记录编号、试验接线图、电压和电流测量点、测量系统型号参数、试验记录格式。\n\n摘要：本文讲述了变压器振荡型操作冲击感应耐压试验中，试验记录应包含的内容，包括被试变压器的相关信息、试验场地的环境条件、每个绕组的冲击试验情况，以及试验记录的格式要求。"
        },
        {
          "title": "2",
          "summary": "知识点：变压器振荡型操作冲击感应耐压试验导则、规范性引用文件、注日期的引用文件、不注日期的引用文件、GB/T311.1、绝缘配合、GB/T1094.3、电力变压器、GB/T2900.19、电工术语、GB/T16896.1、高电压冲击测量仪器和软件、GB/T16927.1、高电压试验技术、GB/T16927.2、测量系统、GB/T16927.3、现场试验的定义及要求、GB26860、电力安全工作规程、GB50148、电气装置安装工程、DL/T848.5、高压试验装置通用技术条件\n\n摘要：本段落介绍了《变压器振荡型操作冲击感应耐压试验导则》中规范性引用的文件，包括注日期和不注日期的引用文件，列出了具体引用的文件标准编号及其内容。"
        },
        {
          "title": "3",
          "summary": "知识点：变压器振荡型操作冲击感应耐压试验、术语和定义、GB/T311.1、GB/T 1094.3、GB/T 2900.19、GB/T 16927.1、本标准\n\n摘要：本段内容介绍了关于变压器振荡型操作冲击感应耐压试验的相关术语和定义，并指出这些术语和定义遵循了GB/T311.1、GB/T 1094.3、GB/T 2900.19、GB/T 16927.1等标准，同时适用于本标准。"
        },
        {
          "title": "4",
          "summary": "知识点：变压器振荡型操作冲击、感应耐压试验、双指数冲击电压、串联电感线圈、电路参数调整、振荡操作冲击电压波形、低幅值冲击电压、高压侧感应、试验原理、主电容、触发球隙、波尾电阻、波头电阻、调波电感、低压侧漏电感、高压侧漏电感、励磁电感、高压侧等效电容\n\n摘要：本段内容介绍了变压器振荡型操作冲击感应耐压试验的原理，通过在双指数冲击电压产生平台的高压回路中串联电感线圈，调整电路参数，产生振荡操作冲击电压波形，并在被试变压器低压侧输入低幅值冲击电压，高压侧感应产生满足试验要求的振荡操作冲击电压。具体原理包括电路中的各个元件及其功能，如主电容、触发球隙、波尾电阻等。"
        },
        {
          "title": "5",
          "summary": "知识点：变压器、振荡型操作冲击、感应耐压试验、导则、试验条件\n\n摘要：本段内容讲述了关于变压器振荡型操作冲击感应耐压试验的相关导则，重点涉及试验所需的条件。"
        },
        {
          "title": "6",
          "summary": "知识点：变压器、振荡型操作冲击、感应耐压试验、导则、试验装置\n\n摘要：本段内容讲述了关于变压器振荡型操作冲击感应耐压试验的导则以及试验装置的相关信息。"
        },
        {
          "title": "7",
          "summary": "知识点：变压器、振荡型操作冲击、感应耐压试验、导则、试验接线、要求\n\n摘要：本段内容讲述了关于变压器振荡型操作冲击感应耐压试验的导则，包括试验的接线方式和具体要求。"
        },
        {
          "title": "8",
          "summary": "知识点：变压器、振荡型操作冲击、感应耐压试验、导则、试验方法\n摘要：本段内容讲述了关于变压器在进行振荡型操作冲击感应耐压试验时的相关导则和试验方法。"
        },
        {
          "title": "9",
          "summary": "知识点：变压器振荡型操作冲击感应耐压试验、结果判断、被试变压器、绕组异常噪声、套管、烟雾、火花放电、电压电流波形、幅值、正比例变化、电压波形、振荡频率、电流波形、电压传递函数、极值点频率、油色谱分析、异常。\n\n摘要：本段内容讲述了变压器振荡型操作冲击感应耐压试验的结果判断标准，包括被试变压器绕组无异常噪声、套管无可见烟雾或火花放电，电压电流波形幅值正比例变化，电压传递函数极值点频率无改变，以及试验后油色谱分析无异常等要求。"
        }
      ]
    }
  },
  "0aef81f4-93cd-4d45-b1e3-cc42b62e0670": {
    "id": "0aef81f4-93cd-4d45-b1e3-cc42b62e0670",
    "parent_id": "f4ad28eb-3dc6-4833-a62b-c49d2dd9e491",
    "level": 1,
    "title": "1",
    "block_number": "1",
    "knowledge_summary": "知识点：变压器振荡型操作冲击感应耐压试验、试验原理、试验条件、试验方法、结果判断、试验记录、110kV～750kV电压等级、油浸式电力变压器\n\n摘要：本文件规定了变压器振荡型操作冲击感应耐压试验的相关要求，包括试验原理、条件、方法、结果判断及记录等，适用于110kV～750kV电压等级的油浸式电力变压器，其他电压等级变压器可参考使用。",
    "page_content": "变压器振荡型操作冲击感应耐压试验导则 > 范围 本文件规定了变压器振荡型操作冲击感应耐压试验（以下简称“振荡操作冲击试验”）的试验原理、试验条件、试验方法、结果判断及试验记录等要求。本文件适用于110kV～750kV 电压等级油浸式电力变压器进行振荡操作冲击试验，其他电压等级变压器可参考使用。",
    "children": [],
    "embedding": [],
    "metadata": {
      "original_level": 1
    }
  },
  "6be5faaa-3b9d-4661-b10b-f7aa3826734c": {
    "id": "6be5faaa-3b9d-4661-b10b-f7aa3826734c",
    "parent_id": "f4ad28eb-3dc6-4833-a62b-c49d2dd9e491",
    "level": 1,
    "title": "10",
    "block_number": "10",
    "knowledge_summary": "知识点：变压器振荡型操作冲击感应耐压试验、试验记录、振荡操作冲击试验记录、被试变压器型号、制造厂家、出厂编号、出厂日期、试验场地温湿度、试验工作地点、日期、绕组冲击试验情况、振荡冲击发生器配置参数、被试绕组电压波形、波头时间、波尾时间、振荡频率、电压幅值、波形记录编号、试验接线图、电压和电流测量点、测量系统型号参数、试验记录格式。\n\n摘要：本文讲述了变压器振荡型操作冲击感应耐压试验中，试验记录应包含的内容，包括被试变压器的相关信息、试验场地的环境条件、每个绕组的冲击试验情况，以及试验记录的格式要求。",
    "page_content": "变压器振荡型操作冲击感应耐压试验导则 > 试验记录 振荡操作冲击试验记录至少应包括以下内容：a)一般内容： 被试变压器的型号、制造厂家、出厂编号、出厂日期； 试验场地的温湿度； 试验的工作地点、日期。 b)每个绕组的冲击试验情况： 振荡冲击发生器的配置参数； 被试绕组电压波形、波头时间、波尾时间、振荡频率、电压幅值； 波形记录编号； 每次试验的接线图； 电压和电流测量点及其测量布置； 测量系统型号参数。 c)试验记录格式见附录E。",
    "children": [],
    "embedding": [],
    "metadata": {
      "original_level": 1
    }
  },
  "4c7eafdf-a3f0-41e0-9f66-3be7c810e534": {
    "id": "4c7eafdf-a3f0-41e0-9f66-3be7c810e534",
    "parent_id": "f4ad28eb-3dc6-4833-a62b-c49d2dd9e491",
    "level": 1,
    "title": "2",
    "block_number": "2",
    "knowledge_summary": "知识点：变压器振荡型操作冲击感应耐压试验导则、规范性引用文件、注日期的引用文件、不注日期的引用文件、GB/T311.1、绝缘配合、GB/T1094.3、电力变压器、GB/T2900.19、电工术语、GB/T16896.1、高电压冲击测量仪器和软件、GB/T16927.1、高电压试验技术、GB/T16927.2、测量系统、GB/T16927.3、现场试验的定义及要求、GB26860、电力安全工作规程、GB50148、电气装置安装工程、DL/T848.5、高压试验装置通用技术条件\n\n摘要：本段落介绍了《变压器振荡型操作冲击感应耐压试验导则》中规范性引用的文件，包括注日期和不注日期的引用文件，列出了具体引用的文件标准编号及其内容。",
    "page_content": "变压器振荡型操作冲击感应耐压试验导则 > 规范性引用文件 下列文件中的内容通过文中的规范性引用而构成本标准必不可少的条款。其中，注日期的引用文件，仅该日期对应的版本适用于本文件；不注日期的引用文件，其最新版本（包括所有的修改单）适用于本文件。GB/T311.1  绝缘配合  第 1 部分：定义、原则和规则 GB/T1094.3  电力变压器  第 3 部分：绝缘水平、绝缘试验和外绝缘空气间隙 GB/T2900.19  电工术语  高电压试验技术和绝缘配合 GB/T16896.1  高电压冲击测量仪器和软件  第 1 部分：对仪器的要求 GB/T16927.1  高电压试验技术  第 1 部分：一般定义及试验要求 GB/T16927.2  高电压试验技术  第 2 部分：测量系统 GB/T16927.3  高电压试验技术  第 3 部分：现场试验的定义及要求 GB26860  电力安全工作规程  发电厂和变电站电气部分 GB50148  电气装置安装工程  电力变压器、油浸电抗器、互感器施工及验收规范 DL/T848.5  高压试验装置通用技术条件  第 5 部分冲击电压发生器",
    "children": [],
    "embedding": [],
    "metadata": {
      "original_level": 1
    }
  },
  "0ebb8e1a-444c-4c4c-b9e8-5b7da82a9dcd": {
    "id": "0ebb8e1a-444c-4c4c-b9e8-5b7da82a9dcd",
    "parent_id": "f4ad28eb-3dc6-4833-a62b-c49d2dd9e491",
    "level": 1,
    "title": "3",
    "block_number": "3",
    "knowledge_summary": "知识点：变压器振荡型操作冲击感应耐压试验、术语和定义、GB/T311.1、GB/T 1094.3、GB/T 2900.19、GB/T 16927.1、本标准\n\n摘要：本段内容介绍了关于变压器振荡型操作冲击感应耐压试验的相关术语和定义，并指出这些术语和定义遵循了GB/T311.1、GB/T 1094.3、GB/T 2900.19、GB/T 16927.1等标准，同时适用于本标准。\n\n【子节点综合】\n知识点: 变压器振荡型操作冲击感应耐压试验、术语和定义、GB/T311.1、GB/T 1094.3、GB/T 2900.19、GB/T 16927.1、振荡型操作冲击、oscillating switching impulse、电压上升、峰值、阻尼振荡、频率范围、电压极性反转、包络线、振荡频率、电压传递函数、快速傅里叶变换、时域信号、频域信号、高压绕组、低压绕组\n\n摘要: 当前章节详细介绍了变压器振荡型操作冲击感应耐压试验的相关术语和定义，引用了多个国家标准，并对振荡型操作冲击的电压特性、振荡频率、电压极性反转等进行了详细描述。此外，还涉及到电压传递函数、快速傅里叶变换在时域信号和频域信号转换中的应用，以及高压绕组和低压绕组电压的比较。",
    "page_content": "变压器振荡型操作冲击感应耐压试验导则 > 术语和定义 GB/T311.1、GB/T 1094.3、GB/T 2900.19、GB/T 16927.1 界定的以及下列术语和定义适用于本标准。",
    "children": [
      "2036d989-8da9-486e-bd51-1046259776eb",
      "61a4c281-c897-4fd9-b55e-5f9ad7e79390"
    ],
    "embedding": [],
    "metadata": {
      "original_level": 1,
      "child_knowledge": [
        {
          "title": "3.1",
          "summary": "知识点：变压器振荡型操作冲击感应耐压试验、术语和定义、GB/T311.1、GB/T 1094.3、GB/T 2900.19、GB/T 16927.1、振荡型操作冲击、oscillating switching impulse、电压上升、峰值、阻尼振荡、频率范围、电压极性反转、包络线、振荡频率。\n\n摘要：本段讲述了变压器振荡型操作冲击感应耐压试验的相关术语和定义，包括引用的多个国家标准，并对振荡型操作冲击进行了详细描述，包括电压特性、振荡频率以及可能出现的电压极性反转等。"
        },
        {
          "title": "3.2",
          "summary": "知识点：变压器振荡型操作冲击感应耐压试验、术语和定义、GB/T311.1、GB/T 1094.3、GB/T 2900.19、GB/T 16927.1、电压传递函数、快速傅里叶变换、时域信号、频域信号、高压绕组、低压绕组\n\n摘要：本段落讲述了变压器振荡型操作冲击感应耐压试验的标准术语和定义，引用了多个相关国家标准，并定义了电压传递函数的概念，涉及快速傅里叶变换将时域信号转换为频域信号，以及高压绕组和低压绕组电压的比较。"
        }
      ]
    }
  },
  "2036d989-8da9-486e-bd51-1046259776eb": {
    "id": "2036d989-8da9-486e-bd51-1046259776eb",
    "parent_id": "0ebb8e1a-444c-4c4c-b9e8-5b7da82a9dcd",
    "level": 2,
    "title": "3.1",
    "block_number": "3.1",
    "knowledge_summary": "知识点：变压器振荡型操作冲击感应耐压试验、术语和定义、GB/T311.1、GB/T 1094.3、GB/T 2900.19、GB/T 16927.1、振荡型操作冲击、oscillating switching impulse、电压上升、峰值、阻尼振荡、频率范围、电压极性反转、包络线、振荡频率。\n\n摘要：本段讲述了变压器振荡型操作冲击感应耐压试验的相关术语和定义，包括引用的多个国家标准，并对振荡型操作冲击进行了详细描述，包括电压特性、振荡频率以及可能出现的电压极性反转等。",
    "page_content": "变压器振荡型操作冲击感应耐压试验导则 > 术语和定义 GB/T311.1、GB/T 1094.3、GB/T 2900.19、GB/T 16927.1 界定的以及下列术语和定义适用于本标准 > 振荡型操作冲击oscillating switching impulse 电压迅速上升到峰值，然后伴随着频率范围在1 kHz 和 15 kHz 之间的阻尼振荡降低至零，其中有或无电压极性的反转，其特性可用包络线和振荡频率描述。",
    "children": [],
    "embedding": [],
    "metadata": {
      "original_level": 2
    }
  },
  "61a4c281-c897-4fd9-b55e-5f9ad7e79390": {
    "id": "61a4c281-c897-4fd9-b55e-5f9ad7e79390",
    "parent_id": "0ebb8e1a-444c-4c4c-b9e8-5b7da82a9dcd",
    "level": 2,
    "title": "3.2",
    "block_number": "3.2",
    "knowledge_summary": "知识点：变压器振荡型操作冲击感应耐压试验、术语和定义、GB/T311.1、GB/T 1094.3、GB/T 2900.19、GB/T 16927.1、电压传递函数、快速傅里叶变换、时域信号、频域信号、高压绕组、低压绕组\n\n摘要：本段落讲述了变压器振荡型操作冲击感应耐压试验的标准术语和定义，引用了多个相关国家标准，并定义了电压传递函数的概念，涉及快速傅里叶变换将时域信号转换为频域信号，以及高压绕组和低压绕组电压的比较。",
    "page_content": "变压器振荡型操作冲击感应耐压试验导则 > 术语和定义 GB/T311.1、GB/T 1094.3、GB/T 2900.19、GB/T 16927.1 界定的以及下列术语和定义适用于本标准 > 电压传递函数voltage transfer function 变压器高压绕组电压和低压绕组电压进行快速傅里叶变换，将时域信号转换为对应的频域信号，并将高压绕组频域信号与低压绕组频域信号作比。DL/TXXXX—202X",
    "children": [],
    "embedding": [],
    "metadata": {
      "original_level": 2
    }
  },
  "90f98a93-810a-44ac-9ca6-02be4955865f": {
    "id": "90f98a93-810a-44ac-9ca6-02be4955865f",
    "parent_id": "f4ad28eb-3dc6-4833-a62b-c49d2dd9e491",
    "level": 1,
    "title": "4",
    "block_number": "4",
    "knowledge_summary": "知识点：变压器振荡型操作冲击、感应耐压试验、双指数冲击电压、串联电感线圈、电路参数调整、振荡操作冲击电压波形、低幅值冲击电压、高压侧感应、试验原理、主电容、触发球隙、波尾电阻、波头电阻、调波电感、低压侧漏电感、高压侧漏电感、励磁电感、高压侧等效电容\n\n摘要：本段内容介绍了变压器振荡型操作冲击感应耐压试验的原理，通过在双指数冲击电压产生平台的高压回路中串联电感线圈，调整电路参数，产生振荡操作冲击电压波形，并在被试变压器低压侧输入低幅值冲击电压，高压侧感应产生满足试验要求的振荡操作冲击电压。具体原理包括电路中的各个元件及其功能，如主电容、触发球隙、波尾电阻等。",
    "page_content": "变压器振荡型操作冲击感应耐压试验导则 > 试验原理 通过在双指数冲击电压产生平台的高压回路中串联电感线圈，调整电路参数，可产生振荡操作冲击电压波形，在被试变压器低压侧输入一个低幅值冲击电压，在其高压侧感应产生满足变压器试验要求的振荡操作冲击电压，试验原理如图1所示，详细原理见附录A。图中：C0——主电容；G——触发球隙；Rt——波尾电阻；Rf——波头电阻；La——调波电感；L1——低压侧漏电感；L2——高压侧漏电感；Lm——励磁电感；C2——高压侧等效电容。",
    "children": [],
    "embedding": [],
    "metadata": {
      "original_level": 1
    }
  },
  "4a1efec3-5c40-49b5-90a9-aaa3027ccf8a": {
    "id": "4a1efec3-5c40-49b5-90a9-aaa3027ccf8a",
    "parent_id": "f4ad28eb-3dc6-4833-a62b-c49d2dd9e491",
    "level": 1,
    "title": "5",
    "block_number": "5",
    "knowledge_summary": "知识点：变压器、振荡型操作冲击、感应耐压试验、导则、试验条件\n\n摘要：本段内容讲述了关于变压器振荡型操作冲击感应耐压试验的相关导则，重点涉及试验所需的条件。\n\n【子节点综合】\n知识点: 变压器振荡型操作冲击感应耐压试验、试验条件、正常环境条件、温度、湿度、海拔、污秽等级、凝露、沉积物、标准参考大气条件、标准温度、标准压力、绝对湿度、振荡操作冲击发生器、被试变压器、特殊环境条件、导则、试品条件、回路条件\n\n摘要: 当前章节详细阐述了变压器振荡型操作冲击感应耐压试验的多个关键条件，包括正常环境条件如温度、湿度、海拔、污秽等级等，以及标准参考大气条件下的标准温度、压力和绝对湿度。此外，还涵盖了试验中使用的振荡操作冲击发生器和被试变压器，以及特殊环境条件下的试验导则、试品条件和回路条件。",
    "page_content": "变压器振荡型操作冲击感应耐压试验导则 > 试验条件",
    "children": [
      "a8d4c803-4070-42bf-85cb-54cc01a74ac3",
      "b9383a79-28bc-4339-becd-fecab5cef136",
      "15c7f199-839a-4a86-ac83-06c32927da2f",
      "5f6b2b7f-9481-4ec3-8eb3-1c799e234033",
      "cb53fb53-9d9c-4567-b72c-834a228271d6"
    ],
    "embedding": [],
    "metadata": {
      "original_level": 1,
      "child_knowledge": [
        {
          "title": "5.1",
          "summary": "知识点：变压器振荡型操作冲击感应耐压试验、试验条件、正常环境条件、温度、湿度、海拔、污秽等级、凝露、沉积物\n摘要：本段讲述了进行变压器振荡型操作冲击感应耐压试验时，所要求的正常环境条件，包括温度不超过35℃，湿度不超过80%，海拔不超过1000m，污秽等级不超过C级，并允许出现凝露和沉积物。"
        },
        {
          "title": "5.2",
          "summary": "知识点：变压器振荡型操作冲击感应耐压试验、试验条件、标准参考大气条件、标准温度、标准压力、绝对湿度、C0C2LaL1RtRfGL2Lm振荡操作冲击发生器、被试变压器\n\n摘要：本段落讲述了变压器振荡型操作冲击感应耐压试验的试验条件，其中包括了标准参考大气条件，包括标准温度、标准压力和绝对湿度，以及测试中涉及的振荡操作冲击发生器和被试变压器。"
        },
        {
          "title": "5.3",
          "summary": "知识点：变压器、振荡型操作冲击、感应耐压试验、导则、试验条件、特殊环境条件、DL/TXXXX—202X\n\n摘要：本段内容讲述了关于变压器振荡型操作冲击感应耐压试验的导则，特别指出试验条件中的特殊环境条件，并提及标准编号为DL/TXXXX—202X。"
        },
        {
          "title": "5.4",
          "summary": "知识点：变压器、振荡型操作冲击、感应耐压试验、导则、试验条件、试品条件\n\n摘要：本段内容讲述了关于变压器振荡型操作冲击感应耐压试验的导则，具体涉及了试验条件和试品条件的相关内容。"
        },
        {
          "title": "5.5",
          "summary": "知识点：变压器、振荡型操作冲击、感应耐压试验、导则、试验条件、回路条件\n\n摘要：本段内容讲述了关于变压器振荡型操作冲击感应耐压试验的导则，重点介绍了试验条件和回路条件的相关内容。"
        }
      ]
    }
  },
  "a8d4c803-4070-42bf-85cb-54cc01a74ac3": {
    "id": "a8d4c803-4070-42bf-85cb-54cc01a74ac3",
    "parent_id": "4a1efec3-5c40-49b5-90a9-aaa3027ccf8a",
    "level": 2,
    "title": "5.1",
    "block_number": "5.1",
    "knowledge_summary": "知识点：变压器振荡型操作冲击感应耐压试验、试验条件、正常环境条件、温度、湿度、海拔、污秽等级、凝露、沉积物\n摘要：本段讲述了进行变压器振荡型操作冲击感应耐压试验时，所要求的正常环境条件，包括温度不超过35℃，湿度不超过80%，海拔不超过1000m，污秽等级不超过C级，并允许出现凝露和沉积物。",
    "page_content": "变压器振荡型操作冲击感应耐压试验导则 > 试验条件  > 正常环境条件 图1基本原理示意图 进行振荡操作冲击试验的正常环境条件如下：a)温度：周围空气温度不超过40℃且24h内测到的平均值不超过35℃； b)湿度：周围空气相对湿度不超过80%； c)海拔：不超过1000m； d)污秽：周围空气没有显著地被灰尘、烟雾、腐蚀性气体、蒸汽或盐雾污染，污秽等级不超过C级污秽；e)其他：允许出现凝露和沉积，考虑了以露水、凝露、雾、雨、雪或积霜形式出现的沉积物。",
    "children": [],
    "embedding": [],
    "metadata": {
      "original_level": 2
    }
  },
  "b9383a79-28bc-4339-becd-fecab5cef136": {
    "id": "b9383a79-28bc-4339-becd-fecab5cef136",
    "parent_id": "4a1efec3-5c40-49b5-90a9-aaa3027ccf8a",
    "level": 2,
    "title": "5.2",
    "block_number": "5.2",
    "knowledge_summary": "知识点：变压器振荡型操作冲击感应耐压试验、试验条件、标准参考大气条件、标准温度、标准压力、绝对湿度、C0C2LaL1RtRfGL2Lm振荡操作冲击发生器、被试变压器\n\n摘要：本段落讲述了变压器振荡型操作冲击感应耐压试验的试验条件，其中包括了标准参考大气条件，包括标准温度、标准压力和绝对湿度，以及测试中涉及的振荡操作冲击发生器和被试变压器。",
    "page_content": "变压器振荡型操作冲击感应耐压试验导则 > 试验条件  > 标准参考大气条件 标准参考大气条件为：a)标准温度：20℃； b)标准压力：101.3kPa； c)绝对湿度：11g/m3。 C0C2LaL1RtRfGL2Lm振荡操作冲击发生器被试变压器",
    "children": [],
    "embedding": [],
    "metadata": {
      "original_level": 2
    }
  },
  "15c7f199-839a-4a86-ac83-06c32927da2f": {
    "id": "15c7f199-839a-4a86-ac83-06c32927da2f",
    "parent_id": "4a1efec3-5c40-49b5-90a9-aaa3027ccf8a",
    "level": 2,
    "title": "5.3",
    "block_number": "5.3",
    "knowledge_summary": "知识点：变压器、振荡型操作冲击、感应耐压试验、导则、试验条件、特殊环境条件、DL/TXXXX—202X\n\n摘要：本段内容讲述了关于变压器振荡型操作冲击感应耐压试验的导则，特别指出试验条件中的特殊环境条件，并提及标准编号为DL/TXXXX—202X。\n\n【子节点综合】\n知识点: 变压器振荡型操作冲击感应耐压试验、试验条件、特殊环境条件、DL/TXXXX—202X、环境空气温度、外绝缘、干燥状态、试验电压、额定耐受电压值、温度修正因数、KT、摄氏度、周围空气相对湿度、湿度修正因数、修正方法、GB/T 16927.1\n\n摘要: 当前章节详细介绍了在特殊环境条件下进行变压器振荡型操作冲击感应耐压试验的相关要求，包括如何根据环境空气温度和相对湿度调整试验电压，涉及温度修正因数KT和湿度修正因数的计算方法，以及GB/T 16927.1标准的遵循。这些内容旨在确保在非标准环境条件下，变压器的外绝缘能够承受正确的试验电压，以评估其绝缘性能。",
    "page_content": "变压器振荡型操作冲击感应耐压试验导则 > 试验条件  > 特殊环境条件 DL/TXXXX—202X",
    "children": [
      "363a93aa-dad6-461e-9f74-1b8a339e8981",
      "c5ae1fec-a43d-451d-984b-3cf0311764c2"
    ],
    "embedding": [],
    "metadata": {
      "original_level": 2,
      "child_knowledge": [
        {
          "title": "5.3.1",
          "summary": "知识点：变压器振荡型操作冲击感应耐压试验、试验条件、特殊环境条件、DL/TXXXX—202X、环境空气温度、外绝缘、干燥状态、试验电压、额定耐受电压值、温度修正因数、KT、摄氏度\n摘要：本段落讲述了在特殊环境条件下，对环境周围空气温度高于40℃的变压器进行振荡型操作冲击感应耐压试验时，外绝缘在干燥状态下的试验电压应如何计算，并给出了温度修正因数KT的计算公式。"
        },
        {
          "title": "5.3.2",
          "summary": "知识点：变压器振荡型操作冲击感应耐压试验、试验条件、特殊环境条件、DL/TXXXX—202X、周围空气相对湿度、外绝缘试验电压、额定耐受电压值、湿度修正因数、修正方法、GB/T 16927.1\n\n摘要：本段讲述了在变压器振荡型操作冲击感应耐压试验中，针对周围空气相对湿度超过80%的特殊环境条件，外绝缘试验电压的确定方法，包括使用额定耐受电压值乘以湿度修正因数，并遵循GB/T 16927.1的规定进行修正。"
        }
      ]
    }
  },
  "363a93aa-dad6-461e-9f74-1b8a339e8981": {
    "id": "363a93aa-dad6-461e-9f74-1b8a339e8981",
    "parent_id": "15c7f199-839a-4a86-ac83-06c32927da2f",
    "level": 3,
    "title": "5.3.1",
    "block_number": "5.3.1",
    "knowledge_summary": "知识点：变压器振荡型操作冲击感应耐压试验、试验条件、特殊环境条件、DL/TXXXX—202X、环境空气温度、外绝缘、干燥状态、试验电压、额定耐受电压值、温度修正因数、KT、摄氏度\n摘要：本段落讲述了在特殊环境条件下，对环境周围空气温度高于40℃的变压器进行振荡型操作冲击感应耐压试验时，外绝缘在干燥状态下的试验电压应如何计算，并给出了温度修正因数KT的计算公式。",
    "page_content": "变压器振荡型操作冲击感应耐压试验导则 > 试验条件  > 特殊环境条件 DL/TXXXX—202X  > 对环境周围空气温度高于 40℃的设备，其外绝缘在干燥状态下的试验电压应取本部分的额定耐受电压值乘以温度修正因数KT。 KT=1+0.0033（T-40）·········································（1）式中：T——环境空气温度，单位为摄氏度（℃）。",
    "children": [],
    "embedding": [],
    "metadata": {
      "original_level": 3
    }
  },
  "c5ae1fec-a43d-451d-984b-3cf0311764c2": {
    "id": "c5ae1fec-a43d-451d-984b-3cf0311764c2",
    "parent_id": "15c7f199-839a-4a86-ac83-06c32927da2f",
    "level": 3,
    "title": "5.3.2",
    "block_number": "5.3.2",
    "knowledge_summary": "知识点：变压器振荡型操作冲击感应耐压试验、试验条件、特殊环境条件、DL/TXXXX—202X、周围空气相对湿度、外绝缘试验电压、额定耐受电压值、湿度修正因数、修正方法、GB/T 16927.1\n\n摘要：本段讲述了在变压器振荡型操作冲击感应耐压试验中，针对周围空气相对湿度超过80%的特殊环境条件，外绝缘试验电压的确定方法，包括使用额定耐受电压值乘以湿度修正因数，并遵循GB/T 16927.1的规定进行修正。",
    "page_content": "变压器振荡型操作冲击感应耐压试验导则 > 试验条件  > 特殊环境条件 DL/TXXXX—202X  > 对于周围空气相对湿度超过 80%的设备，其外绝缘的试验电压应取本部分的额定耐受电压值乘以湿度修正因数，修正方法应符合GB/T 16927.1 的规定。",
    "children": [],
    "embedding": [],
    "metadata": {
      "original_level": 3
    }
  },
  "5f6b2b7f-9481-4ec3-8eb3-1c799e234033": {
    "id": "5f6b2b7f-9481-4ec3-8eb3-1c799e234033",
    "parent_id": "4a1efec3-5c40-49b5-90a9-aaa3027ccf8a",
    "level": 2,
    "title": "5.4",
    "block_number": "5.4",
    "knowledge_summary": "知识点：变压器、振荡型操作冲击、感应耐压试验、导则、试验条件、试品条件\n\n摘要：本段内容讲述了关于变压器振荡型操作冲击感应耐压试验的导则，具体涉及了试验条件和试品条件的相关内容。\n\n【子节点综合】\n知识点: 变压器振荡型操作冲击感应耐压试验、试验条件、试品条件、绝缘特性测量、电压比测量、油耐压试验、标准、静置、静置时间、GB 50148、绝缘强度、GB/T 311.1、分接开关、最大分接档位、电流互感器、二次绕组、短接、接地\n\n摘要: 当前章节详细介绍了进行变压器振荡型操作冲击感应耐压试验所需的各项条件，包括试品的绝缘特性、电压比和油耐压试验结果需符合标准，试验前的试品静置时间应遵循GB 50148标准，被试变压器套管外绝缘强度需满足GB/T 311.1规定，以及试品的具体条件如分接开关位置、电流互感器二次绕组短接和接地等。",
    "page_content": "变压器振荡型操作冲击感应耐压试验导则 > 试验条件  > 试品条件",
    "children": [
      "2cb9a49e-b8ea-42ba-a38d-f3623c79f31e",
      "1e74aa5e-60ea-49e6-9944-74d12b6d0de4",
      "1f5bd3de-f83b-4337-a46a-82d0fd8f2d46",
      "700d5ae7-fd01-4e9b-8923-919906ee1728"
    ],
    "embedding": [],
    "metadata": {
      "original_level": 2,
      "child_knowledge": [
        {
          "title": "5.4.1",
          "summary": "知识点：变压器振荡型操作冲击感应耐压试验、试验条件、试品条件、绝缘特性测量、电压比测量、油耐压试验、标准\n\n摘要：本段讲述了在进行变压器振荡型操作冲击感应耐压试验前，必须确认试品的绝缘特性测量、电压比测量和油耐压试验结果符合标准，满足相关条件后方可进行试验。"
        },
        {
          "title": "5.4.2",
          "summary": "知识点：变压器、振荡型操作冲击、感应耐压试验、导则、试验条件、试品条件、静置、静置时间、GB 50148\n摘要：本段内容讲述了在进行变压器振荡型操作冲击感应耐压试验时，试验前的试品静置条件，包括静置时间和依据的标准GB 50148。"
        },
        {
          "title": "5.4.3",
          "summary": "知识点：变压器振荡型操作冲击感应耐压试验、试验条件、试品条件、被试变压器套管外绝缘、绝缘强度、GB/T 311.1 规定\n摘要：本段讲述了进行变压器振荡型操作冲击感应耐压试验时，被试变压器套管外绝缘的绝缘强度应符合GB/T 311.1规定的条件。"
        },
        {
          "title": "5.4.4",
          "summary": "知识点：变压器振荡型操作冲击感应耐压试验、试验条件、试品条件、被试变压器、分接开关、最大分接档位、电流互感器、二次绕组、短接、接地\n\n摘要：本段落讲述了变压器振荡型操作冲击感应耐压试验中，对试品条件的具体规定，包括被试变压器需满足的条件，如分接开关应处于最大分接档位，所有安装的电流互感器二次绕组需短接并接地。"
        }
      ]
    }
  },
  "2cb9a49e-b8ea-42ba-a38d-f3623c79f31e": {
    "id": "2cb9a49e-b8ea-42ba-a38d-f3623c79f31e",
    "parent_id": "5f6b2b7f-9481-4ec3-8eb3-1c799e234033",
    "level": 3,
    "title": "5.4.1",
    "block_number": "5.4.1",
    "knowledge_summary": "知识点：变压器振荡型操作冲击感应耐压试验、试验条件、试品条件、绝缘特性测量、电压比测量、油耐压试验、标准\n\n摘要：本段讲述了在进行变压器振荡型操作冲击感应耐压试验前，必须确认试品的绝缘特性测量、电压比测量和油耐压试验结果符合标准，满足相关条件后方可进行试验。",
    "page_content": "变压器振荡型操作冲击感应耐压试验导则 > 试验条件  > 试品条件  > 本试验应在绝缘特性测量、电压比测量、油耐压试验的结果得到确认并满足标准后方可进行。",
    "children": [],
    "embedding": [],
    "metadata": {
      "original_level": 3
    }
  },
  "1e74aa5e-60ea-49e6-9944-74d12b6d0de4": {
    "id": "1e74aa5e-60ea-49e6-9944-74d12b6d0de4",
    "parent_id": "5f6b2b7f-9481-4ec3-8eb3-1c799e234033",
    "level": 3,
    "title": "5.4.2",
    "block_number": "5.4.2",
    "knowledge_summary": "知识点：变压器、振荡型操作冲击、感应耐压试验、导则、试验条件、试品条件、静置、静置时间、GB 50148\n摘要：本段内容讲述了在进行变压器振荡型操作冲击感应耐压试验时，试验前的试品静置条件，包括静置时间和依据的标准GB 50148。",
    "page_content": "变压器振荡型操作冲击感应耐压试验导则 > 试验条件  > 试品条件  > 试验前应将被试变压器静置，静置时间应符合 GB 50148 的规定。",
    "children": [],
    "embedding": [],
    "metadata": {
      "original_level": 3
    }
  },
  "1f5bd3de-f83b-4337-a46a-82d0fd8f2d46": {
    "id": "1f5bd3de-f83b-4337-a46a-82d0fd8f2d46",
    "parent_id": "5f6b2b7f-9481-4ec3-8eb3-1c799e234033",
    "level": 3,
    "title": "5.4.3",
    "block_number": "5.4.3",
    "knowledge_summary": "知识点：变压器振荡型操作冲击感应耐压试验、试验条件、试品条件、被试变压器套管外绝缘、绝缘强度、GB/T 311.1 规定\n摘要：本段讲述了进行变压器振荡型操作冲击感应耐压试验时，被试变压器套管外绝缘的绝缘强度应符合GB/T 311.1规定的条件。",
    "page_content": "变压器振荡型操作冲击感应耐压试验导则 > 试验条件  > 试品条件  > 被试变压器套管外绝缘的绝缘强度应符合 GB/T 311.1 的规定。",
    "children": [],
    "embedding": [],
    "metadata": {
      "original_level": 3
    }
  },
  "700d5ae7-fd01-4e9b-8923-919906ee1728": {
    "id": "700d5ae7-fd01-4e9b-8923-919906ee1728",
    "parent_id": "5f6b2b7f-9481-4ec3-8eb3-1c799e234033",
    "level": 3,
    "title": "5.4.4",
    "block_number": "5.4.4",
    "knowledge_summary": "知识点：变压器振荡型操作冲击感应耐压试验、试验条件、试品条件、被试变压器、分接开关、最大分接档位、电流互感器、二次绕组、短接、接地\n\n摘要：本段落讲述了变压器振荡型操作冲击感应耐压试验中，对试品条件的具体规定，包括被试变压器需满足的条件，如分接开关应处于最大分接档位，所有安装的电流互感器二次绕组需短接并接地。",
    "page_content": "变压器振荡型操作冲击感应耐压试验导则 > 试验条件  > 试品条件  > 被试变压器还应符合以下规定： a)分接开关应处于最大分接档位； b)安装的所有电流互感器，二次绕组应短接并接地。",
    "children": [],
    "embedding": [],
    "metadata": {
      "original_level": 3
    }
  },
  "cb53fb53-9d9c-4567-b72c-834a228271d6": {
    "id": "cb53fb53-9d9c-4567-b72c-834a228271d6",
    "parent_id": "4a1efec3-5c40-49b5-90a9-aaa3027ccf8a",
    "level": 2,
    "title": "5.5",
    "block_number": "5.5",
    "knowledge_summary": "知识点：变压器、振荡型操作冲击、感应耐压试验、导则、试验条件、回路条件\n\n摘要：本段内容讲述了关于变压器振荡型操作冲击感应耐压试验的导则，重点介绍了试验条件和回路条件的相关内容。\n\n【子节点综合】\n知识点: 变压器振荡型操作冲击感应耐压试验、试验条件、回路条件、现场试验、被试变压器套管接线端子、电气设备引线、断开、安全距离、GB 26860、短接、下地、试验回路、接地线、一点接地\n\n摘要: 本章节详细介绍了变压器振荡型操作冲击感应耐压试验的试验条件和回路条件，包括现场试验操作要求、被试变压器套管接线端子与电气设备引线的断开、安全距离、短接和下地等，以及试验回路中的接地线连接方式和接地要求，强调需遵守GB 26860的相关规定。",
    "page_content": "变压器振荡型操作冲击感应耐压试验导则 > 试验条件  > 回路条件",
    "children": [
      "cdbc49ba-07d3-4c35-ae1b-38bf94c56eb2",
      "bf7d4eed-0edd-4082-b5dd-8c41f15e37e7"
    ],
    "embedding": [],
    "metadata": {
      "original_level": 2,
      "child_knowledge": [
        {
          "title": "5.5.1",
          "summary": "知识点：变压器振荡型操作冲击感应耐压试验、试验条件、回路条件、现场试验、被试变压器套管接线端子、电气设备引线、断开、安全距离、GB 26860、短接、下地\n\n摘要：本段讲述了变压器振荡型操作冲击感应耐压试验中的试验条件，特别是回路条件下的现场试验操作要求，包括被试变压器套管接线端子与电气设备引线的断开、安全距离及电气设备引线的短接和下地，需遵守GB 26860的规定。"
        },
        {
          "title": "5.5.2",
          "summary": "知识点：变压器振荡型操作冲击感应耐压试验、试验条件、回路条件、试验回路、接地线、一点接地\n\n摘要：本段内容讲述了在进行变压器振荡型操作冲击感应耐压试验时，试验回路中的接地线连接方式和接地要求，即所有接地线应连接在一起后共同接地。"
        }
      ]
    }
  },
  "cdbc49ba-07d3-4c35-ae1b-38bf94c56eb2": {
    "id": "cdbc49ba-07d3-4c35-ae1b-38bf94c56eb2",
    "parent_id": "cb53fb53-9d9c-4567-b72c-834a228271d6",
    "level": 3,
    "title": "5.5.1",
    "block_number": "5.5.1",
    "knowledge_summary": "知识点：变压器振荡型操作冲击感应耐压试验、试验条件、回路条件、现场试验、被试变压器套管接线端子、电气设备引线、断开、安全距离、GB 26860、短接、下地\n\n摘要：本段讲述了变压器振荡型操作冲击感应耐压试验中的试验条件，特别是回路条件下的现场试验操作要求，包括被试变压器套管接线端子与电气设备引线的断开、安全距离及电气设备引线的短接和下地，需遵守GB 26860的规定。",
    "page_content": "变压器振荡型操作冲击感应耐压试验导则 > 试验条件  > 回路条件  > 现场试验时，被试变压器套管接线端子应与所连接电气设备引线断开，断开安全距离应符合GB 26860的规定，电气设备引线应短接下地。",
    "children": [],
    "embedding": [],
    "metadata": {
      "original_level": 3
    }
  },
  "bf7d4eed-0edd-4082-b5dd-8c41f15e37e7": {
    "id": "bf7d4eed-0edd-4082-b5dd-8c41f15e37e7",
    "parent_id": "cb53fb53-9d9c-4567-b72c-834a228271d6",
    "level": 3,
    "title": "5.5.2",
    "block_number": "5.5.2",
    "knowledge_summary": "知识点：变压器振荡型操作冲击感应耐压试验、试验条件、回路条件、试验回路、接地线、一点接地\n\n摘要：本段内容讲述了在进行变压器振荡型操作冲击感应耐压试验时，试验回路中的接地线连接方式和接地要求，即所有接地线应连接在一起后共同接地。",
    "page_content": "变压器振荡型操作冲击感应耐压试验导则 > 试验条件  > 回路条件  > 试验回路中，所有接地线应连接在一起后一点接地。",
    "children": [],
    "embedding": [],
    "metadata": {
      "original_level": 3
    }
  },
  "bdf655ea-0632-4b98-8514-2e269df0503e": {
    "id": "bdf655ea-0632-4b98-8514-2e269df0503e",
    "parent_id": "f4ad28eb-3dc6-4833-a62b-c49d2dd9e491",
    "level": 1,
    "title": "6",
    "block_number": "6",
    "knowledge_summary": "知识点：变压器、振荡型操作冲击、感应耐压试验、导则、试验装置\n\n摘要：本段内容讲述了关于变压器振荡型操作冲击感应耐压试验的导则以及试验装置的相关信息。\n\n【子节点综合】\n知识点: 变压器振荡型操作冲击感应耐压试验、试验装置、振荡操作冲击电压发生器本体、控制系统、测量装置\n摘要: 当前章节详细介绍了变压器振荡型操作冲击感应耐压试验的相关导则，包括试验装置的构成要素，如振荡操作冲击电压发生器本体、控制系统以及测量装置等，为进行此类耐压试验提供了技术指导。",
    "page_content": "变压器振荡型操作冲击感应耐压试验导则 > 试验装置",
    "children": [
      "c0db49db-a321-4582-a7f9-808b5e314069",
      "86d5ae7f-2546-468d-8fdb-73f504acdeb2"
    ],
    "embedding": [],
    "metadata": {
      "original_level": 1,
      "child_knowledge": [
        {
          "title": "6.1",
          "summary": "知识点：变压器振荡型操作冲击感应耐压试验、试验装置、振荡操作冲击电压发生器本体\n\n摘要：本段内容讲述了关于变压器振荡型操作冲击感应耐压试验的导则，具体涉及到试验装置的组成部分，包括振荡操作冲击电压发生器的本体。"
        },
        {
          "title": "6.2",
          "summary": "知识点：变压器振荡型操作冲击感应耐压试验、试验装置、控制系统、测量装置\n\n摘要：本段内容讲述了关于变压器振荡型操作冲击感应耐压试验的导则，涉及试验所需的装置，包括控制系统和测量装置。"
        }
      ]
    }
  },
  "c0db49db-a321-4582-a7f9-808b5e314069": {
    "id": "c0db49db-a321-4582-a7f9-808b5e314069",
    "parent_id": "bdf655ea-0632-4b98-8514-2e269df0503e",
    "level": 2,
    "title": "6.1",
    "block_number": "6.1",
    "knowledge_summary": "知识点：变压器振荡型操作冲击感应耐压试验、试验装置、振荡操作冲击电压发生器本体\n\n摘要：本段内容讲述了关于变压器振荡型操作冲击感应耐压试验的导则，具体涉及到试验装置的组成部分，包括振荡操作冲击电压发生器的本体。\n\n【子节点综合】\n知识点: 变压器振荡型操作冲击感应耐压试验、试验装置、振荡操作冲击电压发生器本体、一般要求、接地标识、外壳保护、防晕屏蔽、充电电压测量误差、接地保护装置、极性转换功能、绝缘强度、绝缘部件、电阻、DL/T 848.5规定、绝缘要求\n\n摘要: 当前章节主要讨论了变压器振荡型操作冲击感应耐压试验中，振荡操作冲击电压发生器本体的一般技术要求，包括接地标识、外壳保护措施、防晕屏蔽、充电电压测量误差控制、接地保护装置和极性转换功能，以及绝缘强度和绝缘部件应满足的DL/T 848.5规定和整体绝缘要求。",
    "page_content": "变压器振荡型操作冲击感应耐压试验导则 > 试验装置  > 振荡操作冲击电压发生器本体",
    "children": [
      "b19bba86-c750-423d-9aa2-ea5901893e58",
      "75d4202e-2dcf-4968-a949-7cbb06d06171"
    ],
    "embedding": [],
    "metadata": {
      "original_level": 2,
      "child_knowledge": [
        {
          "title": "6.1.1",
          "summary": "知识点：变压器振荡型操作冲击感应耐压试验、试验装置、振荡操作冲击电压发生器本体、一般要求、接地符号、表面接地字样、外壳涂漆、防晕屏蔽罩、充电电压测量误差、接地保护装置、极性转换功能\n\n摘要：本段讲述了变压器振荡型操作冲击感应耐压试验中，振荡操作冲击电压发生器本体的一般要求，包括接地标识、外壳保护、防晕屏蔽、充电电压测量误差、接地保护以及极性转换功能等。"
        },
        {
          "title": "6.1.2",
          "summary": "知识点：变压器振荡型操作冲击感应耐压试验、试验装置、振荡操作冲击电压发生器、绝缘强度、绝缘部件、电阻、DL/T 848.5 规定、绝缘要求\n\n摘要：本段内容讲述了变压器振荡型操作冲击感应耐压试验中，试验装置的振荡操作冲击电压发生器本体的绝缘强度要求，指出其绝缘部件和电阻应符合DL/T 848.5的规定，且本体的绝缘强度需满足整个振荡操作冲击电压发生器的绝缘要求。"
        }
      ]
    }
  },
  "b19bba86-c750-423d-9aa2-ea5901893e58": {
    "id": "b19bba86-c750-423d-9aa2-ea5901893e58",
    "parent_id": "c0db49db-a321-4582-a7f9-808b5e314069",
    "level": 3,
    "title": "6.1.1",
    "block_number": "6.1.1",
    "knowledge_summary": "知识点：变压器振荡型操作冲击感应耐压试验、试验装置、振荡操作冲击电压发生器本体、一般要求、接地符号、表面接地字样、外壳涂漆、防晕屏蔽罩、充电电压测量误差、接地保护装置、极性转换功能\n\n摘要：本段讲述了变压器振荡型操作冲击感应耐压试验中，振荡操作冲击电压发生器本体的一般要求，包括接地标识、外壳保护、防晕屏蔽、充电电压测量误差、接地保护以及极性转换功能等。",
    "page_content": "变压器振荡型操作冲击感应耐压试验导则 > 试验装置  > 振荡操作冲击电压发生器本体  > 一般要求 振荡操作冲击电压发生器本体一般要求为：a)应有明显的接地符号或表面接地字样； b)外壳应涂漆保护，应无明显损伤； c)尖端部位应设置防晕屏蔽罩； d)充电电压测量误差应小于1%； e)冲击发生器电容器应具备接地保护装置； f)应具备极性转换功能，能进行正负极性转换。",
    "children": [],
    "embedding": [],
    "metadata": {
      "original_level": 3
    }
  },
  "75d4202e-2dcf-4968-a949-7cbb06d06171": {
    "id": "75d4202e-2dcf-4968-a949-7cbb06d06171",
    "parent_id": "c0db49db-a321-4582-a7f9-808b5e314069",
    "level": 3,
    "title": "6.1.2",
    "block_number": "6.1.2",
    "knowledge_summary": "知识点：变压器振荡型操作冲击感应耐压试验、试验装置、振荡操作冲击电压发生器、绝缘强度、绝缘部件、电阻、DL/T 848.5 规定、绝缘要求\n\n摘要：本段内容讲述了变压器振荡型操作冲击感应耐压试验中，试验装置的振荡操作冲击电压发生器本体的绝缘强度要求，指出其绝缘部件和电阻应符合DL/T 848.5的规定，且本体的绝缘强度需满足整个振荡操作冲击电压发生器的绝缘要求。",
    "page_content": "变压器振荡型操作冲击感应耐压试验导则 > 试验装置  > 振荡操作冲击电压发生器本体  > 绝缘强度 振荡操作冲击电压发生器的绝缘部件和电阻应符合DL/T 848.5 的规定，本体的绝缘强度应满足整个振荡操作冲击电压发生器的绝缘要求。",
    "children": [],
    "embedding": [],
    "metadata": {
      "original_level": 3
    }
  },
  "86d5ae7f-2546-468d-8fdb-73f504acdeb2": {
    "id": "86d5ae7f-2546-468d-8fdb-73f504acdeb2",
    "parent_id": "bdf655ea-0632-4b98-8514-2e269df0503e",
    "level": 2,
    "title": "6.2",
    "block_number": "6.2",
    "knowledge_summary": "知识点：变压器振荡型操作冲击感应耐压试验、试验装置、控制系统、测量装置\n\n摘要：本段内容讲述了关于变压器振荡型操作冲击感应耐压试验的导则，涉及试验所需的装置，包括控制系统和测量装置。\n\n【子节点综合】\n知识点: 变压器振荡型操作冲击感应耐压试验、试验装置、控制系统、测量装置、振荡操作冲击电压发生器、电气操作、机械操作、控制箱、手动控制、自动控制、按钮功能、指示灯、紧急停止按钮、接地点、隔离变压器供电、触发点火装置、自动接地保护装置、动作可靠性、测量系统、测量要求、GB/T 16927.2、GB/T 16896.1、分压器、电压波形测量、套管试验抽头、小电容、电压传递函数计算功能\n\n摘要: 当前章节详细介绍了变压器振荡型操作冲击感应耐压试验中试验装置的控制系统和测量装置的要求，包括控制系统的操作方式、安全功能、供电方式、点火装置和接地保护装置的动作可靠性，以及测量系统的标准要求、测量设备的选择和必须具备的功能，如电压传递函数计算等。",
    "page_content": "变压器振荡型操作冲击感应耐压试验导则 > 试验装置  > 控制系统和测量装置",
    "children": [
      "157479e3-c586-4ae3-8b83-ed95141afc54",
      "c5bf7295-8757-43f4-9e95-9d93eaf63845"
    ],
    "embedding": [],
    "metadata": {
      "original_level": 2,
      "child_knowledge": [
        {
          "title": "6.2.1",
          "summary": "知识点：变压器振荡型操作冲击感应耐压试验、试验装置、控制系统、测量装置、振荡操作冲击电压发生器、电气操作、机械操作、控制箱、手动控制、自动控制、按钮功能、指示灯、紧急停止按钮、接地点、隔离变压器供电、触发点火装置、自动接地保护装置、动作可靠性。\n\n摘要：本段内容讲述了变压器振荡型操作冲击感应耐压试验中，试验装置的控制系统和测量装置的要求，包括控制箱的操作、按钮功能、指示灯、紧急停止按钮、接地点、供电方式、点火装置和接地保护装置的动作可靠性等。"
        },
        {
          "title": "6.2.2",
          "summary": "知识点：变压器振荡型操作冲击感应耐压试验、试验装置、控制系统和测量装置、测量系统、振荡操作冲击电压发生器、测量要求、GB/T 16927.2、GB/T 16896.1、分压器、电压波形测量、套管试验抽头、小电容、电压传递函数计算功能\n\n摘要：本段落讲述了变压器振荡型操作冲击感应耐压试验中的测量系统要求，包括应符合的标准、采用的测量设备（如分压器、套管试验抽头和小电容）以及必须具备的功能（电压传递函数计算）。"
        }
      ]
    }
  },
  "157479e3-c586-4ae3-8b83-ed95141afc54": {
    "id": "157479e3-c586-4ae3-8b83-ed95141afc54",
    "parent_id": "86d5ae7f-2546-468d-8fdb-73f504acdeb2",
    "level": 3,
    "title": "6.2.1",
    "block_number": "6.2.1",
    "knowledge_summary": "知识点：变压器振荡型操作冲击感应耐压试验、试验装置、控制系统、测量装置、振荡操作冲击电压发生器、电气操作、机械操作、控制箱、手动控制、自动控制、按钮功能、指示灯、紧急停止按钮、接地点、隔离变压器供电、触发点火装置、自动接地保护装置、动作可靠性。\n\n摘要：本段内容讲述了变压器振荡型操作冲击感应耐压试验中，试验装置的控制系统和测量装置的要求，包括控制箱的操作、按钮功能、指示灯、紧急停止按钮、接地点、供电方式、点火装置和接地保护装置的动作可靠性等。",
    "page_content": "变压器振荡型操作冲击感应耐压试验导则 > 试验装置  > 控制系统和测量装置  > 控制系统 DL/TXXXX—202X 振荡操作冲击电压发生器的所有电气及机械操作均应在控制箱上进行，并要求：a)手动、自动控制的所有按钮功能齐全、准确； b)指示灯应显示准确，无误动作； c)紧急停止按钮应准确，快速动作； d)控制箱应具有良好的接地点，应采用隔离变压器供电； e)触发点火装置应100%可靠动作； f)自动接地保护装置在任何情况应100%动作并可靠接地。",
    "children": [],
    "embedding": [],
    "metadata": {
      "original_level": 3
    }
  },
  "c5bf7295-8757-43f4-9e95-9d93eaf63845": {
    "id": "c5bf7295-8757-43f4-9e95-9d93eaf63845",
    "parent_id": "86d5ae7f-2546-468d-8fdb-73f504acdeb2",
    "level": 3,
    "title": "6.2.2",
    "block_number": "6.2.2",
    "knowledge_summary": "知识点：变压器振荡型操作冲击感应耐压试验、试验装置、控制系统和测量装置、测量系统、振荡操作冲击电压发生器、测量要求、GB/T 16927.2、GB/T 16896.1、分压器、电压波形测量、套管试验抽头、小电容、电压传递函数计算功能\n\n摘要：本段落讲述了变压器振荡型操作冲击感应耐压试验中的测量系统要求，包括应符合的标准、采用的测量设备（如分压器、套管试验抽头和小电容）以及必须具备的功能（电压传递函数计算）。",
    "page_content": "变压器振荡型操作冲击感应耐压试验导则 > 试验装置  > 控制系统和测量装置  > 测量系统 振荡操作冲击电压发生器的测量系统一般要求为：a)应符合GB/T 16927.2和GB/T 16896.1的规定； b)被试变压器低压侧及高压侧宜采用分压器进行电压波形的测量，必要时可采用套管试验抽头并联小电容进行测量；c)应具备电压传递函数计算功能。",
    "children": [],
    "embedding": [],
    "metadata": {
      "original_level": 3
    }
  },
  "032fc5d4-80d7-4c83-b97d-e5419e071ceb": {
    "id": "032fc5d4-80d7-4c83-b97d-e5419e071ceb",
    "parent_id": "f4ad28eb-3dc6-4833-a62b-c49d2dd9e491",
    "level": 1,
    "title": "7",
    "block_number": "7",
    "knowledge_summary": "知识点：变压器、振荡型操作冲击、感应耐压试验、导则、试验接线、要求\n\n摘要：本段内容讲述了关于变压器振荡型操作冲击感应耐压试验的导则，包括试验的接线方式和具体要求。\n\n【子节点综合】\n知识点: 变压器振荡型操作冲击感应耐压试验、试验接线、要求、接线示意图、附录B规定、非被试绕组端子电压峰值、被试绕组端子电压峰值、示波器测量装置、试验电源、隔离变压器、工频耐受电压水平\n\n摘要: 本章节详细介绍了变压器振荡型操作冲击感应耐压试验的接线方法和要求，包括具体的接线示意图和附录B的规定，同时强调了试验过程中非被试绕组端子电压峰值的限制，以及测量装置、试验电源和隔离变压器的选用标准，特别是隔离变压器的工频耐受电压水平应不低于10kV（方均根值）。",
    "page_content": "变压器振荡型操作冲击感应耐压试验导则 > 试验接线及要求",
    "children": [
      "96fb4caa-6c04-4d1d-9a87-da2e645b3ee3",
      "85944922-7eb3-40fb-a595-2158dfa12fc4"
    ],
    "embedding": [],
    "metadata": {
      "original_level": 1,
      "child_knowledge": [
        {
          "title": "7.1",
          "summary": "知识点：变压器振荡型操作冲击感应耐压试验、试验接线、要求、接线示意图、附录B规定\n\n摘要：本段内容讲述了变压器振荡型操作冲击感应耐压试验的试验接线及要求，具体接线方法可参考图2和附录B的规定。"
        },
        {
          "title": "7.2",
          "summary": "知识点：变压器振荡型操作冲击感应耐压试验、试验接线及要求、试验要求、110kV及以上电压等级、三相变压器试验、非被试绕组端子电压峰值、被试绕组端子电压峰值、示波器测量装置、试验电源、隔离变压器、工频耐受电压水平\n摘要：本文讲述了变压器振荡型操作冲击感应耐压试验中的试验接线及要求，包括试验时应注意的非被试绕组端子电压峰值限制以及测量装置与试验电源的隔离要求，特别指出了采用隔离变压器时其工频耐受电压水平应不低于10kV（方均根值）。"
        }
      ]
    }
  },
  "96fb4caa-6c04-4d1d-9a87-da2e645b3ee3": {
    "id": "96fb4caa-6c04-4d1d-9a87-da2e645b3ee3",
    "parent_id": "032fc5d4-80d7-4c83-b97d-e5419e071ceb",
    "level": 2,
    "title": "7.1",
    "block_number": "7.1",
    "knowledge_summary": "知识点：变压器振荡型操作冲击感应耐压试验、试验接线、要求、接线示意图、附录B规定\n\n摘要：本段内容讲述了变压器振荡型操作冲击感应耐压试验的试验接线及要求，具体接线方法可参考图2和附录B的规定。",
    "page_content": "变压器振荡型操作冲击感应耐压试验导则 > 试验接线及要求  > 试验接线 变压器进行振荡操作冲击试验接线示意图如图2 所示，具体接线按附录 B 规定。",
    "children": [],
    "embedding": [],
    "metadata": {
      "original_level": 2
    }
  },
  "85944922-7eb3-40fb-a595-2158dfa12fc4": {
    "id": "85944922-7eb3-40fb-a595-2158dfa12fc4",
    "parent_id": "032fc5d4-80d7-4c83-b97d-e5419e071ceb",
    "level": 2,
    "title": "7.2",
    "block_number": "7.2",
    "knowledge_summary": "知识点：变压器振荡型操作冲击感应耐压试验、试验接线及要求、试验要求、110kV及以上电压等级、三相变压器试验、非被试绕组端子电压峰值、被试绕组端子电压峰值、示波器测量装置、试验电源、隔离变压器、工频耐受电压水平\n摘要：本文讲述了变压器振荡型操作冲击感应耐压试验中的试验接线及要求，包括试验时应注意的非被试绕组端子电压峰值限制以及测量装置与试验电源的隔离要求，特别指出了采用隔离变压器时其工频耐受电压水平应不低于10kV（方均根值）。",
    "page_content": "变压器振荡型操作冲击感应耐压试验导则 > 试验接线及要求  > 试验要求 图2振荡操作冲击试验接线示意图 振荡操作冲击试验应符合以下规定：a)110kV及以上电压等级三相变压器试验时，非被试绕组端子电压峰值不应超出被试绕组端子电压峰值的50%；b)示波器等测量装置应与试验电源有效隔离，若采用隔离变压器，其工频耐受电压水平应不低于10kV（方均根值）。",
    "children": [],
    "embedding": [],
    "metadata": {
      "original_level": 2
    }
  },
  "c2c75d3f-5a32-4e84-850d-4c7d3a654653": {
    "id": "c2c75d3f-5a32-4e84-850d-4c7d3a654653",
    "parent_id": "f4ad28eb-3dc6-4833-a62b-c49d2dd9e491",
    "level": 1,
    "title": "8",
    "block_number": "8",
    "knowledge_summary": "知识点：变压器、振荡型操作冲击、感应耐压试验、导则、试验方法\n摘要：本段内容讲述了关于变压器在进行振荡型操作冲击感应耐压试验时的相关导则和试验方法。\n\n【子节点综合】\n知识点: 变压器振荡型操作冲击感应耐压试验、试验方法、试验波形、GB/T 16927.3、GB/T 16927.1、典型振荡操作冲击电压波形、附录C、试验电源、振荡操作冲击电压发生器、示波器、abcABCO分压器、测试电阻、被试变压器、波形关键参数、峰值时间、半峰值时间、振荡频率、试验电压、DL/T标准、试验流程\n\n摘要: 当前章节详细介绍了变压器振荡型操作冲击感应耐压试验的方法，包括试验波形应符合国家标准GB/T 16927.3和GB/T 16927.1，并遵循附录C中典型的振荡操作冲击电压波形。此外，还阐述了试验电源、设备参数、波形关键参数（如峰值时间、半峰值时间、振荡频率）以及试验电压和遵循的DL/T标准，并概述了试验的流程和导则。",
    "page_content": "变压器振荡型操作冲击感应耐压试验导则 > 试验方法",
    "children": [
      "09b67e4b-3326-4d37-a310-d874e7658692",
      "42ec85d7-88bf-4f57-95e6-54d2ccf4cdc2",
      "902f224d-dbf7-4233-be67-d44d715c5d88"
    ],
    "embedding": [],
    "metadata": {
      "original_level": 1,
      "child_knowledge": [
        {
          "title": "8.1",
          "summary": "知识点：变压器振荡型操作冲击感应耐压试验、试验方法、试验波形、GB/T 16927.3、GB/T 16927.1、典型振荡操作冲击电压波形、附录C、试验电源、振荡操作冲击电压发生器、示波器、abcABCO分压器、测试电阻、被试变压器、波形关键参数、峰值时间、半峰值时间、振荡频率。\n\n摘要：本段讲述了变压器振荡型操作冲击感应耐压试验的试验方法，包括试验波形应符合GB/T 16927.3规定，波形确定方法应符合GB/T 16927.1规定，并应遵循附录C中的典型振荡操作冲击电压波形。此外，还提到了试验中使用的电源、设备参数以及波形的关键参数范围。"
        },
        {
          "title": "8.2",
          "summary": "知识点：变压器振荡型操作冲击感应耐压试验、试验方法、试验电压、DL/T标准\n\n摘要：本段内容讲述了关于变压器振荡型操作冲击感应耐压试验的导则，具体涉及到试验方法和试验电压，以及该测试方法所遵循的DL/T标准编号。"
        },
        {
          "title": "8.3",
          "summary": "知识点：变压器、振荡型操作冲击、感应耐压试验、导则、试验方法、试验流程\n\n摘要：本段内容讲述了关于变压器振荡型操作冲击感应耐压试验的导则，包括试验的具体方法和流程。"
        }
      ]
    }
  },
  "09b67e4b-3326-4d37-a310-d874e7658692": {
    "id": "09b67e4b-3326-4d37-a310-d874e7658692",
    "parent_id": "c2c75d3f-5a32-4e84-850d-4c7d3a654653",
    "level": 2,
    "title": "8.1",
    "block_number": "8.1",
    "knowledge_summary": "知识点：变压器振荡型操作冲击感应耐压试验、试验方法、试验波形、GB/T 16927.3、GB/T 16927.1、典型振荡操作冲击电压波形、附录C、试验电源、振荡操作冲击电压发生器、示波器、abcABCO分压器、测试电阻、被试变压器、波形关键参数、峰值时间、半峰值时间、振荡频率。\n\n摘要：本段讲述了变压器振荡型操作冲击感应耐压试验的试验方法，包括试验波形应符合GB/T 16927.3规定，波形确定方法应符合GB/T 16927.1规定，并应遵循附录C中的典型振荡操作冲击电压波形。此外，还提到了试验中使用的电源、设备参数以及波形的关键参数范围。",
    "page_content": "变压器振荡型操作冲击感应耐压试验导则 > 试验方法  > 试验波形 振荡操作冲击试验施加到被试绕组的电压波形应符合GB/T 16927.3 的规定，确定波形的方法应符合GB/T16927.1 的规定，典型振荡操作冲击电压波形应符合附录 C 规定。 试验电源振荡操作冲击电压发生器示波器abcABCO分压器测试电阻被试变压器波形关键参数如下：a)峰值时间：20µs～400µs； b)半峰值时间：1000µs～4000µs； c)振荡频率：1kHz～15kHz。",
    "children": [],
    "embedding": [],
    "metadata": {
      "original_level": 2
    }
  },
  "42ec85d7-88bf-4f57-95e6-54d2ccf4cdc2": {
    "id": "42ec85d7-88bf-4f57-95e6-54d2ccf4cdc2",
    "parent_id": "c2c75d3f-5a32-4e84-850d-4c7d3a654653",
    "level": 2,
    "title": "8.2",
    "block_number": "8.2",
    "knowledge_summary": "知识点：变压器振荡型操作冲击感应耐压试验、试验方法、试验电压、DL/T标准\n\n摘要：本段内容讲述了关于变压器振荡型操作冲击感应耐压试验的导则，具体涉及到试验方法和试验电压，以及该测试方法所遵循的DL/T标准编号。\n\n【子节点综合】\n知识点: 变压器振荡型操作冲击感应耐压试验、试验方法、试验电压、DL/TXXXX—202X、电压等级、振荡操作冲击试验电压水平、表1、系统标称电压、设备最高电压、双指数操作冲击、振荡型操作冲击、方均根值、峰值、相对地、技术协议、试验电压偏差、被试变压器、100%试验电压水平、全新变压器出厂试验、翻新变压器出厂试验、变电站组装、发电厂组装、现场交接试验、诊断性试验、主绝缘、纵绝缘、引线绝缘缺陷\n\n摘要: 本章节详细介绍了变压器振荡型操作冲击感应耐压试验的方法和标准，包括试验电压的规范（DL/TXXXX—202X）、不同电压等级下的试验电压水平、操作冲击电压的调整以及试验电压偏差的要求。此外，还涵盖了不同类型变压器在不同组装和运行阶段（如全新和翻新变压器、变电站和发电厂组装、现场交接和诊断性试验）下的试验要求，以及针对主绝缘、纵绝缘和引线绝缘缺陷的试验标准。",
    "page_content": "变压器振荡型操作冲击感应耐压试验导则 > 试验方法  > 试验电压 DL/TXXXX—202X",
    "children": [
      "d228dd20-8d93-4ef6-917c-04369b24cb23",
      "01e55ddc-4cc9-45c1-ab36-27271b74d761",
      "1e9089ed-6468-4211-bf6f-1829db07baed"
    ],
    "embedding": [],
    "metadata": {
      "original_level": 2,
      "child_knowledge": [
        {
          "title": "8.2.1",
          "summary": "知识点：变压器振荡型操作冲击感应耐压试验、试验方法、试验电压、DL/TXXXX—202X、电压等级、振荡操作冲击试验电压水平、表1、系统标称电压、设备最高电压、双指数操作冲击、振荡型操作冲击、方均根值、峰值、相对地、技术协议、试验电压偏差\n\n摘要：本段内容讲述了变压器振荡型操作冲击感应耐压试验的试验方法，包括试验电压的标准（DL/TXXXX—202X）、不同电压等级的振荡操作冲击试验电压水平应符合表1规定，以及试验电压的测量值与规定值的偏差要求。此外，还提到了根据技术协议调整操作冲击电压的要求。"
        },
        {
          "title": "8.2.2",
          "summary": "知识点：变压器振荡型操作冲击感应耐压试验、试验方法、试验电压、DL/TXXXX—202X、被试变压器、100%试验电压水平、振荡操作冲击试验、全新变压器出厂试验、翻新变压器出厂试验、变电站组装、发电厂组装\n\n摘要：本段讲述了变压器振荡型操作冲击感应耐压试验的相关内容，包括试验方法、试验电压标准，以及在不同情况下（如全新变压器、翻新变压器在变电站或发电厂组装）进行100%试验电压水平的振荡操作冲击试验的要求。"
        },
        {
          "title": "8.2.3",
          "summary": "知识点：变压器振荡型操作冲击感应耐压试验、试验方法、试验电压、DL/TXXXX—202X、现场交接试验、诊断性试验、主绝缘、纵绝缘、引线绝缘缺陷\n\n摘要：本段内容介绍了变压器振荡型操作冲击感应耐压试验的相关规定，包括试验电压标准DL/TXXXX—202X，以及在不同情况下，如投运前、检修后及怀疑存在绝缘缺陷时，应进行的80%试验电压水平的振荡操作冲击试验。"
        }
      ]
    }
  },
  "d228dd20-8d93-4ef6-917c-04369b24cb23": {
    "id": "d228dd20-8d93-4ef6-917c-04369b24cb23",
    "parent_id": "42ec85d7-88bf-4f57-95e6-54d2ccf4cdc2",
    "level": 3,
    "title": "8.2.1",
    "block_number": "8.2.1",
    "knowledge_summary": "知识点：变压器振荡型操作冲击感应耐压试验、试验方法、试验电压、DL/TXXXX—202X、电压等级、振荡操作冲击试验电压水平、表1、系统标称电压、设备最高电压、双指数操作冲击、振荡型操作冲击、方均根值、峰值、相对地、技术协议、试验电压偏差\n\n摘要：本段内容讲述了变压器振荡型操作冲击感应耐压试验的试验方法，包括试验电压的标准（DL/TXXXX—202X）、不同电压等级的振荡操作冲击试验电压水平应符合表1规定，以及试验电压的测量值与规定值的偏差要求。此外，还提到了根据技术协议调整操作冲击电压的要求。",
    "page_content": "变压器振荡型操作冲击感应耐压试验导则 > 试验方法  > 试验电压 DL/TXXXX—202X  > 不同电压等级的振荡操作冲击试验电压水平应符合表 1 规定。如无另行规定，振荡操作冲击试验电压水平应与操作冲击试验电压水平一致。表1振荡操作冲击试验电压水平 单位为千伏系统标称电压（方均根值）设备最高电压Um 双指数操作冲击（SI）振荡型操作冲击（方均根值）（峰值，相对地）（峰值，相对地）根据技术协议操作冲击电压另有要求，则试验电压应与技术协议一致；除非另有规定，试验电压的测量值与规定值的偏差应保持在±3%之内。",
    "children": [],
    "embedding": [],
    "metadata": {
      "original_level": 3
    }
  },
  "01e55ddc-4cc9-45c1-ab36-27271b74d761": {
    "id": "01e55ddc-4cc9-45c1-ab36-27271b74d761",
    "parent_id": "42ec85d7-88bf-4f57-95e6-54d2ccf4cdc2",
    "level": 3,
    "title": "8.2.2",
    "block_number": "8.2.2",
    "knowledge_summary": "知识点：变压器振荡型操作冲击感应耐压试验、试验方法、试验电压、DL/TXXXX—202X、被试变压器、100%试验电压水平、振荡操作冲击试验、全新变压器出厂试验、翻新变压器出厂试验、变电站组装、发电厂组装\n\n摘要：本段讲述了变压器振荡型操作冲击感应耐压试验的相关内容，包括试验方法、试验电压标准，以及在不同情况下（如全新变压器、翻新变压器在变电站或发电厂组装）进行100%试验电压水平的振荡操作冲击试验的要求。",
    "page_content": "变压器振荡型操作冲击感应耐压试验导则 > 试验方法  > 试验电压 DL/TXXXX—202X  > 以下情况的被试变压器应在 100%试验电压水平进行振荡操作冲击试验： a)全新变压器的出厂试验； b)翻新变压器（经质保修理或绕组完全重新绕制、重新装配达到全新变压器状态）的出厂试验； c)在变电站、发电厂组装的全新及翻新变压器。",
    "children": [],
    "embedding": [],
    "metadata": {
      "original_level": 3
    }
  },
  "1e9089ed-6468-4211-bf6f-1829db07baed": {
    "id": "1e9089ed-6468-4211-bf6f-1829db07baed",
    "parent_id": "42ec85d7-88bf-4f57-95e6-54d2ccf4cdc2",
    "level": 3,
    "title": "8.2.3",
    "block_number": "8.2.3",
    "knowledge_summary": "知识点：变压器振荡型操作冲击感应耐压试验、试验方法、试验电压、DL/TXXXX—202X、现场交接试验、诊断性试验、主绝缘、纵绝缘、引线绝缘缺陷\n\n摘要：本段内容介绍了变压器振荡型操作冲击感应耐压试验的相关规定，包括试验电压标准DL/TXXXX—202X，以及在不同情况下，如投运前、检修后及怀疑存在绝缘缺陷时，应进行的80%试验电压水平的振荡操作冲击试验。",
    "page_content": "变压器振荡型操作冲击感应耐压试验导则 > 试验方法  > 试验电压 DL/TXXXX—202X  > 以下情况的被试变压器应在 80%试验电压水平进行振荡操作冲击试验： a)投运前的现场交接试验； b)已投运变压器经检修后的诊断性试验； c)怀疑存在主绝缘、纵绝缘及引线绝缘缺陷时。",
    "children": [],
    "embedding": [],
    "metadata": {
      "original_level": 3
    }
  },
  "902f224d-dbf7-4233-be67-d44d715c5d88": {
    "id": "902f224d-dbf7-4233-be67-d44d715c5d88",
    "parent_id": "c2c75d3f-5a32-4e84-850d-4c7d3a654653",
    "level": 2,
    "title": "8.3",
    "block_number": "8.3",
    "knowledge_summary": "知识点：变压器、振荡型操作冲击、感应耐压试验、导则、试验方法、试验流程\n\n摘要：本段内容讲述了关于变压器振荡型操作冲击感应耐压试验的导则，包括试验的具体方法和流程。\n\n【子节点综合】\n知识点: 变压器振荡型操作冲击感应耐压试验、试验方法、试验流程、被试变压器结构型式、接线要求、低压侧、逐相施加、试验电压、负极性电压\n\n摘要: 当前章节详细介绍了变压器振荡型操作冲击感应耐压试验的方法和流程，包括根据被试变压器结构型式进行接线，以及在被试变压器低压侧逐相施加负极性试验电压的具体操作步骤，强调了试验过程中的关键要求和技术细节。",
    "page_content": "变压器振荡型操作冲击感应耐压试验导则 > 试验方法  > 试验流程",
    "children": [
      "c72276c6-803d-465d-bc8a-a3a39473f890",
      "5463d46c-ee37-4104-a993-3b075f981574"
    ],
    "embedding": [],
    "metadata": {
      "original_level": 2,
      "child_knowledge": [
        {
          "title": "8.3.1",
          "summary": "知识点：变压器振荡型操作冲击感应耐压试验、试验方法、试验流程、被试变压器结构型式、接线要求、7.1要求\n\n摘要：本段内容讲述了进行变压器振荡型操作冲击感应耐压试验的方法和流程，强调根据被试变压器的结构型式，按照规定的要求进行接线，具体参照7.1的相关要求。"
        },
        {
          "title": "8.3.2",
          "summary": "知识点：变压器振荡型操作冲击感应耐压试验、试验方法、试验流程、被试变压器、低压侧、逐相施加、试验电压、负极性电压\n\n摘要：本段内容讲述了变压器振荡型操作冲击感应耐压试验的试验方法及流程，指出被试变压器低压侧应逐相施加相应的试验电压，通常采用负极性电压进行测试。"
        }
      ]
    }
  },
  "c72276c6-803d-465d-bc8a-a3a39473f890": {
    "id": "c72276c6-803d-465d-bc8a-a3a39473f890",
    "parent_id": "902f224d-dbf7-4233-be67-d44d715c5d88",
    "level": 3,
    "title": "8.3.1",
    "block_number": "8.3.1",
    "knowledge_summary": "知识点：变压器振荡型操作冲击感应耐压试验、试验方法、试验流程、被试变压器结构型式、接线要求、7.1要求\n\n摘要：本段内容讲述了进行变压器振荡型操作冲击感应耐压试验的方法和流程，强调根据被试变压器的结构型式，按照规定的要求进行接线，具体参照7.1的相关要求。",
    "page_content": "变压器振荡型操作冲击感应耐压试验导则 > 试验方法  > 试验流程  > 根据被试变压器结构型式，按照 7.1 的要求对变压器进行接线。",
    "children": [],
    "embedding": [],
    "metadata": {
      "original_level": 3
    }
  },
  "5463d46c-ee37-4104-a993-3b075f981574": {
    "id": "5463d46c-ee37-4104-a993-3b075f981574",
    "parent_id": "902f224d-dbf7-4233-be67-d44d715c5d88",
    "level": 3,
    "title": "8.3.2",
    "block_number": "8.3.2",
    "knowledge_summary": "知识点：变压器振荡型操作冲击感应耐压试验、试验方法、试验流程、被试变压器、低压侧、逐相施加、试验电压、负极性电压\n\n摘要：本段内容讲述了变压器振荡型操作冲击感应耐压试验的试验方法及流程，指出被试变压器低压侧应逐相施加相应的试验电压，通常采用负极性电压进行测试。",
    "page_content": "变压器振荡型操作冲击感应耐压试验导则 > 试验方法  > 试验流程  > 被试变压器低压侧应逐相施加相应的试验电压，通常施加负极性电压。",
    "children": [],
    "embedding": [],
    "metadata": {
      "original_level": 3
    }
  },
  "9b8b0a35-ad79-4ec5-add7-85287ea573b5": {
    "id": "9b8b0a35-ad79-4ec5-add7-85287ea573b5",
    "parent_id": "f4ad28eb-3dc6-4833-a62b-c49d2dd9e491",
    "level": 1,
    "title": "9",
    "block_number": "9",
    "knowledge_summary": "知识点：变压器振荡型操作冲击感应耐压试验、结果判断、被试变压器、绕组异常噪声、套管、烟雾、火花放电、电压电流波形、幅值、正比例变化、电压波形、振荡频率、电流波形、电压传递函数、极值点频率、油色谱分析、异常。\n\n摘要：本段内容讲述了变压器振荡型操作冲击感应耐压试验的结果判断标准，包括被试变压器绕组无异常噪声、套管无可见烟雾或火花放电，电压电流波形幅值正比例变化，电压传递函数极值点频率无改变，以及试验后油色谱分析无异常等要求。",
    "page_content": "变压器振荡型操作冲击感应耐压试验导则 > 结果判断 试验结果同时满足以下要求，判定该次试验通过。a)被试变压器绕组未出现异常噪声，变压器套管无可见烟雾或火花放电。 b)比较全电压与50%充电电压下的电压、电流波形，幅值按电压大小正比例变化，电压波形未出现突然截断、振荡频率变化，电流波形未出现突然增大。c)比较全电压与50%充电电压下的电压传递函数，电压传递函数极值点频率无改变。 d)试验后静置24小时进行油色谱分析，结果无异常。 试验结果的判断案例见附录D。",
    "children": [],
    "embedding": [],
    "metadata": {
      "original_level": 1
    }
  }
}